{"bank_list":[{"id":"AACX","name":"Akhand Anand Co.op Bank"},{"id":"ABCX","name":"Aurangabad District Central Co-operative Bank"},{"id":"ABDX","name":"Dr. Ambedkar Nagrik Sahakari Bank Mydt Gwalior"},{"id":"ABEX","name":"Andhra Bank Employees Co-operative Bank"},{"id":"ABHY","name":"Abhyudaya Co-operative Bank"},{"id":"ABNA","name":"Royal Bank of Scotland N.V."},{"id":"ABPB","name":"Aditya Birla Idea Payments Bank"},{"id":"ABSB","name":"Abhinav Sahakari Bank"},{"id":"ABUX","name":"Abhinandan Urban Co-operative Bank Amravati"},{"id":"ACAX","name":"Assam Co-operative Apex Bank"},{"id":"ACBX","name":"Adarsh Co-operative Bank"},{"id":"ACCX","name":"Ace Co-operative Bank"},{"id":"ACKX","name":"Annasaheb Chougule Urban Co-operative Bank"},{"id":"ACOX","name":"Amarnath Co-operative Bank"},{"id":"ACUB","name":"Aryapuram Co-operative Urban Bank"},{"id":"ACUX","name":"Adarsh Co-operative Urban Bank"},{"id":"ADBX","name":"Ahmedabad District Co-operative Bank"},{"id":"ADCB","name":"Abu Dhabi Commercial Bank"},{"id":"ADCC","name":"Akola District Central Co-operative Bank"},{"id":"ADCX","name":"Shri Adinath Co-operative Bank"},{"id":"ADDX","name":"Adilabad District Co-operative Central Bank"},{"id":"AGCX","name":"Agrasen Co-operative Urban Bank"},{"id":"AGDX","name":"Agra District Co-operative Bank"},{"id":"AGRX","name":"Agroha Co-operative Urban Bank"},{"id":"AGSX","name":"Agrasen Nagari Sahakari Bank"},{"id":"AGUX","name":"Agartala Co-operative Urban Bank"},{"id":"AGVX","name":"Assam Gramin Vikash Bank"},{"id":"AHMX","name":"Ahmednagar District Central Co-operative Bank"},{"id":"AHUX","name":"Ahilyadevi Urban Co-operative Bank Limited Solapur"},{"id":"AIRP","name":"Airtel Payments Bank"},{"id":"AJHC","name":"Ambarnath Jaihind Co-operative Bank Ambarnath"},{"id":"AJKB","name":"Akola Janata Commercial Co-operative Bank"},{"id":"AJMX","name":"Ajmer Central Co-operative Bank"},{"id":"AJNX","name":"Ajantha Urban Co-operative Bank"},{"id":"AJPX","name":"Ambajogai Peoples Co-operative Bank"},{"id":"AJSX","name":"Ambarnath Jai-hind Co-operative Bank"},{"id":"AJUX","name":"Ajara Urban Co-operative Bank Bom"},{"id":"AKJB","name":"Akola Janata Commercial Co-operative Bank"},{"id":"AKMX","name":"Akola Merchant Co-operative Bank"},{"id":"AKOX","name":"Akola Urban Co-operative Bank"},{"id":"ALAX","name":"Alavi Co-operative Bank"},{"id":"ALIX","name":"Aligarh District Co-operative Bank"},{"id":"ALLA","name":"Allahabad Bank"},{"id":"ALLX","name":"Allahabad District Co-operative Bank"},{"id":"ALWX","name":"Alwar Central Co-operative Bank"},{"id":"AMAX","name":"Aman Sahakari Bank"},{"id":"AMBX","name":"Ambala Central Co-operative Bank"},{"id":"AMCB","name":"Ahmedabad Mercantile Co-operative Bank"},{"id":"AMCX","name":"Amritsar Central Co-operative Bank"},{"id":"AMDN","name":"Ahmednagar Merchants Co-operative Bank"},{"id":"AMMX","name":"Adarsh Mahila Mercantile Co-operative Bank"},{"id":"AMNX","name":"Astha Mahila Nagrik Sahakari Bank Maryadit"},{"id":"AMRX","name":"Amreli Jilla Madhyastha Sahakari Bank"},{"id":"AMSB","name":"Annasaheb Magar Sahakari Bank"},{"id":"AMSX","name":"Ambika Mahila Sahakari Bank Ahmednagar"},{"id":"ANBX","name":"Amreli Nagarik Sahakari Bank"},{"id":"ANDB","name":"Andhra Bank"},{"id":"ANDX","name":"Andarsul Urban Co-operative Bank"},{"id":"ANMX","name":"Ahmednagar Merchant's Co-operative Bank"},{"id":"ANSX","name":"Andaman & Nicobar State Co-operative Bank"},{"id":"ANUX","name":"Anuradha Urban Co-operative Bank"},{"id":"ANZB","name":"Australia and New Zealand Banking Group"},{"id":"APBL","name":"Andhra Pradesh State Co-operative Bank"},{"id":"APCX","name":"Alappuzha District Co-operative Bank"},{"id":"APGB","name":"Andhra Pragathi Grameena Bank"},{"id":"APGV","name":"Andhra Pradesh Grameena Vikas Bank"},{"id":"APGX","name":"Andhra Pradesh Grameena Vikas Bank"},{"id":"APJX","name":"Ap Janata Co-operative Urban Bank"},{"id":"APMC","name":"A.P. Mahesh Co-operative Urban Bank"},{"id":"APMX","name":"Ap Mahajan's Co-operative Urban Bank"},{"id":"APNX","name":"Apani Sahakari Bank"},{"id":"APRX","name":"Arunachal Pradesh Rural Bank"},{"id":"APSX","name":"Adarniya P.d. Patilsaheb Sahakari Bank"},{"id":"ARCX","name":"Arunachal Pradesh State Co-operative Apex Bank"},{"id":"ARMX","name":"510 Army Base W/s Credit Co-operative Primary Bank"},{"id":"ARYX","name":"Gramin Bank of Aryavart"},{"id":"ASBL","name":"Apna Sahakari Bank"},{"id":"ASBX","name":"Ahmednagar Shahar Sahakari Bank Maryadit"},{"id":"ASHX","name":"Ashta People's Co-operative Bank"},{"id":"ASKX","name":"Arvind Sahakari Bank"},{"id":"ASNX","name":"Ashoknagar Co-operative Bank"},{"id":"ASOX","name":"Associate Co-operative Bank"},{"id":"ASSX","name":"Ashok Sahakari Bank"},{"id":"AUBL","name":"AU Small Finance Bank"},{"id":"AUBX","name":"Angul United Central Co-operative Bank"},{"id":"AUCB","name":"Almora Urban Co-operative Bank"},{"id":"AUCX","name":"Ajara Urban Co-operative Bank"},{"id":"AUGX","name":"Allahabad Up Gramin Bank"},{"id":"AURX","name":"Aurangabad District Central Co-operative Bank. Bihar"},{"id":"AVDX","name":"Amravati District Central Co-operative Bank"},{"id":"AWCX","name":"Alwaye Urban Co-operative Bank"},{"id":"AWUX","name":"Alwar Urban Co-operative Bank"},{"id":"AZAX","name":"Azad Co-operative Bank"},{"id":"AZPX","name":"Amravati Zilla Parishad Shikshak Sahakari Bank"},{"id":"AZSX","name":"Almora Zila Sahkari Bank"},{"id":"AZUX","name":"Azad Urban Co-operative Bank Hubli"},{"id":"BACB","name":"Bassein Catholic Co-operative Bank"},{"id":"BACX","name":"Bihar Awami Co-operative Bank"},{"id":"BADX","name":"Bankura District Central Co-operative Bank"},{"id":"BALX","name":"Balasinor Nagarik Sahakari Bank"},{"id":"BANX","name":"Banaras Merchantile Co-operative Bank"},{"id":"BARA","name":"Baramati Sahakari Bank"},{"id":"BARB","name":"Bank of Baroda"},{"id":"BARC","name":"Barclays Bank"},{"id":"BARX","name":"Baroda City Co-operative Bank"},{"id":"BASX","name":"Shri Basaveshwar Sahakari Bank Nyt.bagalkot"},{"id":"BAUX","name":"Badagara Co-operative Urban Bank"},{"id":"BAVX","name":"Bavla Nagrik Sahakari Bank"},{"id":"BBKM","name":"Bank of Bahrein and Kuwait"},{"id":"BBLX","name":"Bhingar Urban Co-operative Bank"},{"id":"BBRX","name":"Bangalore  Bangalore Rural&ramanagara Dccb"},{"id":"BBSX","name":"Balasore Bhadrak Central Co-operative Bank"},{"id":"BBUX","name":"Bellad Bagewadi Urban Souharada Sahakari Bank Nyt"},{"id":"BBVX","name":"Bhabhar Vibhag Nagrik Sahakari Bank"},{"id":"BCBM","name":"Bharat Co-operative Bank"},{"id":"BCBX","name":"Bantra Co-operative Bank"},{"id":"BCCB","name":"Bangalore City Co-operative Bank"},{"id":"BCCX","name":"Bathinda Central Co-operative Bank"},{"id":"BCEX","name":"Banswara Central Co-operative Bank"},{"id":"BCEY","name":"Bank of Ceylon"},{"id":"BCOX","name":"Bapuji Co-operative Bank"},{"id":"BCUB","name":"Bicholim Urban Co-operative Bank"},{"id":"BCUX","name":"Baghat Urban Co-operative Bank"},{"id":"BDBL","name":"Bandhan Bank"},{"id":"BDBX","name":"Bellary District Co-operative Central Bank"},{"id":"BDCX","name":"Bijapur District Central Co-operative Bank"},{"id":"BDDX","name":"Bhadradri Co-operative Urban Bank"},{"id":"BDIX","name":"Bhandara District Central Co-operative Bank"},{"id":"BDNX","name":"Bhind Nagrik Sahakari Bank Mydt"},{"id":"BDOX","name":"Banda District Co-operative Bank Limited Banda"},{"id":"BDUX","name":"Banda Urban Co-operative Bank"},{"id":"BEDX","name":"Beed District Central Co-operative Bank"},{"id":"BELX","name":"Belgaum District Central Co-operative Bank"},{"id":"BFUX","name":"Bhagyodaya Friends Urban Co-operative Bank"},{"id":"BGBX","name":"Bihar Gramin Bank"},{"id":"BGCX","name":"Balageria Central Co-operative Bank"},{"id":"BGGX","name":"Baroda Gujarat Gramin Bank"},{"id":"BGUX","name":"Begusarai Central Co-operative Bank"},{"id":"BGVX","name":"Bangiya Gramin Vikash Bank"},{"id":"BHAX","name":"Bhagyodaya Co-operative Bank"},{"id":"BHBX","name":"Bhilai Nagarik Sahakari Bank Maryadit"},{"id":"BHCX","name":"Bhuj Commercial Co-operative Bank"},{"id":"BHDX","name":"Bhadohi Urban Co-operative Bank Gyanpur"},{"id":"BHEX","name":"Bhel Employees Co-operative Bank"},{"id":"BHGX","name":"Bhagalpur Central Co-operative Bank"},{"id":"BHIX","name":"Bhilwara Mahila Urban Co-operative Bank"},{"id":"BHJX","name":"Bhuj Mercentile Co-operative Bank"},{"id":"BHMX","name":"Brahmadeodada Mane Sahakari Bank Solapur"},{"id":"BHOX","name":"Bhopal Co-operative Central Bank"},{"id":"BHRX","name":"Bharatpur Central Co-operative Bank"},{"id":"BHSX","name":"Bharati Sahakari Bank Pune"},{"id":"BHTX","name":"Bhatkal Urban Co-operative Bank"},{"id":"BHUX","name":"Bhilwara Urban Co-operative Bank"},{"id":"BHWX","name":"Bhiwani Central Co-operative Bank Bhiwani"},{"id":"BJUX","name":"Bijnor Urban Co-operative Bank"},{"id":"BKCX","name":"Bhavasara Kshatriya Co-operative Bank"},{"id":"BKDN","name":"Dena Bank"},{"id":"BKDX","name":"Banaskantha Dist Central Co-operative Bank"},{"id":"BKID","name":"Bank of India"},{"id":"BKSX","name":"Baran Kendriya Sahakari Bank Baran"},{"id":"BLGX","name":"Shree Basaveshwar Co-operative Bank"},{"id":"BMBL","name":"Bharatiya Mahila Bank"},{"id":"BMCB","name":"Bombay Mercantile Co-operative Bank"},{"id":"BMCX","name":"Barmer Central Co-operative Bank"},{"id":"BMPX","name":"Banaskantha Mercantile Co-operative Bank"},{"id":"BMSX","name":"Bhagyalakshmi Mahila Sahakari Bank"},{"id":"BNBX","name":"Betul Nagrik Sahakari Bank Mydt"},{"id":"BNCX","name":"Bhatpara Naihati Co-operative Bank"},{"id":"BNPA","name":"BNP Paribas Bank"},{"id":"BNSB","name":"Bhagini Nivedita Sahakari Bank Pune"},{"id":"BNSX","name":"Bhagini Nivedita Sahakari Bank"},{"id":"BODX","name":"Bagalkot District Central Co-operative Bank"},{"id":"BOFA","name":"Bank of America"},{"id":"BORX","name":"Boral Union Co-operative Bank"},{"id":"BOTM","name":"Bank of Tokyo Mitsubishi"},{"id":"BOTX","name":"Shree Botad Mercantile Co-operative Bank"},{"id":"BPCX","name":"Bhadgaon People's Co-operative Bank"},{"id":"BPSX","name":"Bilagi Pattana Sahakari Bank Niyamit"},{"id":"BRCX","name":"Bhavana Rishi Co-operative. Urban Bank"},{"id":"BRDX","name":"Baroda Central Co-operative Bank"},{"id":"BRGX","name":"Baroda Rajasthan Kshetriya Gramin Bank"},{"id":"BRMX","name":"Bramhapuri Urban Co-operative Bank"},{"id":"BRSX","name":"Baran Nagrik Sahkari Bank"},{"id":"BRUX","name":"Bharuch District Central Co-operative Bank Bharuc"},{"id":"BSBX","name":"Baramati Sahakari Bank"},{"id":"BSCX","name":"Baidyabati Sheoraphuli Co-operative Bank"},{"id":"BTCX","name":"Balitikuri Co-operative Bank"},{"id":"BTUX","name":"Balotra Urban Co-operative Bank"},{"id":"BUBX","name":"Bhandara Urban Co-operative Bank"},{"id":"BUCX","name":"Beawar Urban Co-operative Bank"},{"id":"BUGX","name":"Baroda Uttar Pradesh Gramin Bank"},{"id":"BUNX","name":"Bundi Central Co-operative Bank"},{"id":"BURX","name":"Burdwan Central Co-operative Bank"},{"id":"BUSX","name":"Business Co-operative Bank"},{"id":"BUZX","name":"Badaun Zila Sahkari Bank"},{"id":"BVNX","name":"Bhavnagar District Co-operative Bank"},{"id":"BVSX","name":"Bhavani Sahakari Bank"},{"id":"BWCX","name":"Brahmawart Commercial Co-operative Bank"},{"id":"CALX","name":"Calicut Co-operative Urban Bank"},{"id":"CBHX","name":"Central Co-operative Bank  Bhilwara"},{"id":"CBIN","name":"Central Bank of India"},{"id":"CCBL","name":"Citizen Credit Co-operative Bank"},{"id":"CCBX","name":"Citizen Co-operative Bank"},{"id":"CCCX","name":"Chennai Central Co-operative Bank"},{"id":"CCMX","name":"Chanasma Commercial Co-operative Bank"},{"id":"CCOB","name":"City Co-operative Bank"},{"id":"CCUX","name":"Chengelpattu Co-operative Urban Bank"},{"id":"CDCX","name":"Cuddalore District Central Co-operative Bank"},{"id":"CEBX","name":"Central Co-operative Bank Bikaner"},{"id":"CGBX","name":"Chhattisgarh Gramin Bank"},{"id":"CGGX","name":"Chaitanya Godavari Grameena Bank"},{"id":"CHAS","name":"JP Morgan Chase Bank NA"},{"id":"CHAX","name":"Chamoli Zila Sahkari Bank"},{"id":"CHBX","name":"Chamba Urban Co-operative Bank Chamba"},{"id":"CHCX","name":"Churu Central Co-operative Bank"},{"id":"CHDX","name":"Chittoor District Co-operative Central Bank"},{"id":"CHIX","name":"Chikhli Urban Co-operative Bank"},{"id":"CHKX","name":"Chittorgarh Kendriya Sahakari Bank"},{"id":"CHPX","name":"Chopda Peoples Co-operative Bank"},{"id":"CHRX","name":"Cherpalcheri Co-operative Urban Bank"},{"id":"CHSX","name":"Chandigarh State Co-operative Bank"},{"id":"CHTX","name":"Chitnavispura Sahakari Bank"},{"id":"CIDX","name":"Chikmagalur District Central Co-operative Bank"},{"id":"CITI","name":"CITI Bank"},{"id":"CITX","name":"Chitradurga District Co-operative Central Bank"},{"id":"CIUB","name":"City Union Bank"},{"id":"CJAX","name":"Citizens' Co-operative Bank Jammu"},{"id":"CJMX","name":"Chikmagalur Jilla Mahila Sahakara Bank"},{"id":"CLBL","name":"Capital Small Finance Bank"},{"id":"CMCB","name":"Colour Merchant's Co-operative Bank"},{"id":"CMCX","name":"Commercial Co-operative Bank"},{"id":"CMDX","name":"Coimbatore District Central Co-operative Bank"},{"id":"CMLX","name":"Commercial Co-operative Bank"},{"id":"CMPX","name":"Central Madhya Pradesh Gramin Bank"},{"id":"CNRB","name":"Canara Bank"},{"id":"CNSX","name":"Chembur Nagarik Sahakari Bank"},{"id":"COCX","name":"Co-operative City Bank"},{"id":"COLX","name":"Coastal Local Area Bank"},{"id":"COMX","name":"Co-operative Bank of Mehsana"},{"id":"CONX","name":"Contai Co-operative Bank"},{"id":"CORP","name":"Corporation Bank"},{"id":"COSB","name":"Cosmos Co-operative Bank"},{"id":"CPDX","name":"Chandrapur District Central Co-operative Bank"},{"id":"CRBX","name":"Central Co-operative Bank Ara"},{"id":"CRES","name":"Credit Suisse AG"},{"id":"CRLY","name":"Credit Agricole Corporate and Investment Bank"},{"id":"CRSX","name":"Chhattisgarh Rajya Sahakari Bank Mydt"},{"id":"CRUB","name":"Shri Chhatrapati Rajashri Shahu Urban Co-operative Bank"},{"id":"CSBK","name":"Catholic Syrian Bank"},{"id":"CSBX","name":"Chartered Sahakari Bank Niyamitha"},{"id":"CTBA","name":"Commonwealth Bank of Australia"},{"id":"CTBX","name":"Citizens Co-operative Bank"},{"id":"CTCB","name":"Chinatrust Commercial Bank"},{"id":"CTOX","name":"Central Co-operative Bank Tonk"},{"id":"CTUX","name":"Chittorgarh Urban Co-operative Bank Chittorgarh"},{"id":"CUBX","name":"Catholic Co-operative Urban Bank"},{"id":"CUCX","name":"Chiplun Urban Co-operative Bank"},{"id":"CURX","name":"Citizens Urban Co-operative Bank"},{"id":"CZCX","name":"Citizen Co-operative Bank"},{"id":"CZUX","name":"Churu Zila Urban Co-operative Bank"},{"id":"DAAX","name":"Defence Accounts Co-operative Bank"},{"id":"DAHX","name":"Dahod Mercantile Co-operative Bank"},{"id":"DAUX","name":"Dausa Urban Co-operative Bank"},{"id":"DBAX","name":"Dr Babasaheb Ambedkar Sahakari Bank Nasik"},{"id":"DBSS","name":"Development Bank of Singapore"},{"id":"DCBL","name":"DCB Bank"},{"id":"DCBX","name":"Dindigul Central Co-operative Bank"},{"id":"DCCX","name":"District Co-operative Central Bank Mahabubnagar"},{"id":"DCDX","name":"District Central Co-operative Bank Limited Elluru"},{"id":"DCEX","name":"District Central Co-operativeearative Bank Khammam"},{"id":"DCKX","name":"District Co-operative Central Bank Kurnool"},{"id":"DCMX","name":"District Co-operative Bank Mainpuri"},{"id":"DCNX","name":"Deccan Co-operative Urban Bank"},{"id":"DCPX","name":"District Co-operative Bank Pilibhit"},{"id":"DCSX","name":"District Co-operative Bank Shahjahanpur"},{"id":"DCTX","name":"District Co-operative Bank Teliyabagh"},{"id":"DCUX","name":"Darussalam Co-operative Urban Bank"},{"id":"DDBX","name":"Dharmapuri District Central Co-operative Bank"},{"id":"DDCX","name":"Darjeeling District Central Co-operative Bank"},{"id":"DDDX","name":"Dakshin Dinajpur District Central Co-operative Bank"},{"id":"DDHX","name":"District Co-operative Bank Dehradun"},{"id":"DEGX","name":"Dena Gujarat Gramin Bank"},{"id":"DENS","name":"Delhi Nagrik Sehkari Bank"},{"id":"DEOB","name":"Deogiri Nagari Sahakari Bank Aurangabad"},{"id":"DEOX","name":"Deogiri Sahakari Bank Aurangabad"},{"id":"DEUT","name":"Deutsche Bank"},{"id":"DEUX","name":"Devika Urban Co-operative Bank"},{"id":"DEVX","name":"Development Co-operative Bank Kanpur"},{"id":"DGBX","name":"Telangana Grameena Bank"},{"id":"DHBX","name":"Dhanbad Central Co-operative Bank"},{"id":"DHKX","name":"Dhakuria Co-operative Bank"},{"id":"DHUX","name":"Dahod Urban Co-operative Bank"},{"id":"DIBX","name":"District Co-operative Bank Barabanki"},{"id":"DICG","name":"Deposit Insurance and Credit Guarantee Corporation"},{"id":"DICX","name":"District Co-operative Central Bank Visakhapatnam"},{"id":"DIUX","name":"Dilip Urban Co-operative Bank"},{"id":"DJCX","name":"Deoghar Jamtara Central Co-operative Bank Deoghar"},{"id":"DKSX","name":"Dausa Kendriya Sahkari Bank Dausa"},{"id":"DLSC","name":"Delhi State Co-operative Bank"},{"id":"DLXB","name":"Dhanlaxmi Bank"},{"id":"DMCB","name":"Deccan Merchants Co-operative Bank"},{"id":"DMCX","name":"Durgapur Mahila Co-operative Bank"},{"id":"DMKB","name":"Dattatraya Maharaj Kalambe Jaoli Sahakari Bank"},{"id":"DMKJ","name":"Dmk Jaoli Bank"},{"id":"DNSB","name":"Dombivli Nagari Sahakari Bank"},{"id":"DNSX","name":"Deendayal Nagari Sahakari Bank"},{"id":"DOBX","name":"Dapoli Urban Co-operative Bank Dapoli"},{"id":"DOHB","name":"Doha Bank QSC"},{"id":"DRGX","name":"Durg Rajnandgaon Gramin Bank (merged With Chhattisgarh Rajya Gramin Bank-cgbx)"},{"id":"DSBX","name":"Daivadnya Sahakara Bank Niyamit"},{"id":"DSCB","name":"Delhi State Co-operative Bank"},{"id":"DSHX","name":"District Co-operative Bank Saharanpur"},{"id":"DSPX","name":"Durgapur Steel Peoples' Co-operative Bank"},{"id":"DSUX","name":"Dharamvir Sambhaji Urban Co-operative Bank"},{"id":"DTCX","name":"District Co-operative Bankraebareli"},{"id":"DTPX","name":"District Co-operative Bank Pratapgarh"},{"id":"DUCX","name":"Daund Urban Co-operative Bank"},{"id":"DUMX","name":"Dumka Central Co-operative Bank"},{"id":"DUNX","name":"Dungarpur Central Co-operative Bank"},{"id":"DURG","name":"Durgapur Steel Peoples Co-operative Bank"},{"id":"DVDX","name":"Davanagere District Central Co-operative Bank"},{"id":"DYPX","name":"D.y.patil Sahakari Bank Kolhapur"},{"id":"EBIL","name":"Emirates NBD Bank"},{"id":"ECBL","name":"Excellent Co-operative Bank"},{"id":"EDBX","name":"Ellaquai Dehati Bank"},{"id":"EDCX","name":"Erode District Central Co-operative Bank"},{"id":"EDSX","name":"Ernakulam District Co-operative Bank"},{"id":"EIBI","name":"Export Import Bank of India"},{"id":"ESAF","name":"ESAF Small Finance Bank"},{"id":"ESFB","name":"Equitas Small Finance Bank"},{"id":"ESMF","name":"Esaf Small Finance Bank"},{"id":"ETCX","name":"Etawah District Co-operative Bank Etwah"},{"id":"ETDX","name":"Etah District Co-operative Bank"},{"id":"EUCX","name":"Etah Urban Co-operative Bank"},{"id":"EWCX","name":"Etawah Urban Co-operative Bank Etawah"},{"id":"FCBX","name":"Fazilka Central Co-operative. Bank"},{"id":"FCCX","name":"Faridkot Central Co-operative Bank"},{"id":"FCOX","name":"District Co-Operative Bank Faizabad"},{"id":"FDFX","name":"Farrukhabad District Co-operative Bank Fatehgarh"},{"id":"FDRL","name":"Federal Bank"},{"id":"FEKX","name":"Feroke Co-operative Bank"},{"id":"FGCB","name":"Fingrowth Co-operative Bank"},{"id":"FINO","name":"Fino Payments Bank"},{"id":"FINF","name":"Fincare Small Finance Bank "},{"id":"FINX","name":"Financial Co-operative Bank"},{"id":"FIRN","name":"Firstrand Bank"},{"id":"FIRX","name":"Firstrand Bank"},{"id":"FMCX","name":"Faiz Mercantile Co-operative Bank, Nasik"},{"id":"FRIX","name":"Faridabad Central Co-operative Bank"},{"id":"FSCX","name":"Fatehgrah Sahib Central Co-operative Bank"},{"id":"FSFB","name":"Fincare Small Finance Bank"},{"id":"FZCX","name":"Ferozepur Central Co-operative. Bank"},{"id":"FZSX","name":"Firozabad Zila Sahkari Bank"},{"id":"GACX","name":"Gujarat Ambuja Co-operative Bank"},{"id":"GADX","name":"Gadhinglaj Urban Co-operative Bank"},{"id":"GANX","name":"Gandhidham Co-operative Bank"},{"id":"GBCB","name":"Greater Bombay Co-operative Bank"},{"id":"GCBX","name":"Guruvayur Co-operative Urban Bank"},{"id":"GCCX","name":"Gurdaspur Central Co-operative Bank"},{"id":"GCUL","name":"Gauhati Co-operative Urban Bank"},{"id":"GCUX","name":"Gayatri Co-operative Urban Bank"},{"id":"GDCB","name":"Gadchiroli District Central Co-operative Bank"},{"id":"GDCX","name":"Guntur District Co-operative Central Bank"},{"id":"GDDX","name":"Giridih Central Co-operative Bank"},{"id":"GDUX","name":"Godhra Urban Co-operative Bank"},{"id":"GGBK","name":"Gurgaon Gramin Bank"},{"id":"GGCX","name":"Gopalganj Central Co-operativeertative Bank"},{"id":"GHPX","name":"Ghatal Peoples' Co-operative Bank"},{"id":"GKNX","name":"Ganganagar Kendriya Sahakari Bank"},{"id":"GMBX","name":"Gandhidham Mercantile Co-operative Bank"},{"id":"GMCX","name":"Gujarat Mercantile Co-operative Bank"},{"id":"GMUX","name":"Gulshan Mercantile Urban Co-operative Bank"},{"id":"GNCX","name":"Gandhi Co-operative Urban Bank"},{"id":"GNSX","name":"Gozaria Nagrik Sahakari Bank"},{"id":"GODX","name":"Godavari Urban Co-operative Bank Nashik"},{"id":"GOSX","name":"Gondal Nagarik Sahakari Bank"},{"id":"GPCX","name":"Gandevi People's Co-operative Bank"},{"id":"GPOX","name":"General Post Office"},{"id":"GRAX","name":"Grain Merchants' Co-operative Bank"},{"id":"GSBL","name":"Goa State Co-operative Bank"},{"id":"GSBX","name":"Gandhibag Sahakari Bank  Nagpur"},{"id":"GSCB","name":"Gujarat State Co-operative Bank"},{"id":"GSCX","name":"Gumla Simdega Central Co-operative Bank"},{"id":"GSSX","name":"Guardian Souharda Sahakari Bank Niyamita"},{"id":"GTCX","name":"George Town Co-operative Bank"},{"id":"GUBX","name":"Godavari Urban Co-operative Bank"},{"id":"GUCX","name":"Goa Urban Co-operative Bank"},{"id":"GUNX","name":"Guntur Co-operative Urban Bank"},{"id":"GUOX","name":"Gurgaon Central Co-operative Bank"},{"id":"HAMX","name":"Hamirpur District Co-operative Bank"},{"id":"HANX","name":"Hanumangarh Kendriya Sahakari Bank"},{"id":"HARC","name":"Haryana State Co-operative Apex Bank"},{"id":"HCBL","name":"Hindusthan Co-operative Bank"},{"id":"HCBX","name":"Hasti Co-operative Bank"},{"id":"HCCX","name":"Hazaribag Central Co-operative Bank"},{"id":"HCLX","name":"HCBL Co-operative Bank"},{"id":"HDCX","name":"Hyderabad District Co-operative Bank"},{"id":"HDFC","name":"HDFC Bank"},{"id":"HGBX","name":"Sarva Haryana Gramin Bank"},{"id":"HINX","name":"Hindu Co-operative Bank"},{"id":"HISX","name":"Hisar Central Co-operative Bank Hisar"},{"id":"HMBX","name":"Himachal Gramin Bank"},{"id":"HMNX","name":"Himatnagar Nagarik Sahakari Bank"},{"id":"HOCX","name":"Hoshiarpur Central Co-operative Bank"},{"id":"HOOX","name":"Hooghly District Central Co-operative Bank"},{"id":"HPCX","name":"Shree Parswanath Co-operative Bank"},{"id":"HPSC","name":"Himachal Pradesh State Co-operative Bank"},{"id":"HPSX","name":"Himachal Pradesh State Co-operative Bank"},{"id":"HSBC","name":"Hongkong & Shanghai Banking Corporation"},{"id":"HSBX","name":"Harihareshwar Sahakari Bank"},{"id":"HSCX","name":"Haryana State Co-operative Apex Bank"},{"id":"HSDX","name":"Hassan District Co-operative Central Bank"},{"id":"HSSX","name":"Hindustan Shipyard Staff Co-operative Bank"},{"id":"HUBX","name":"Hubli Urban Co-operative Bank"},{"id":"HUCX","name":"Hissar Urban Co-operative Bank"},{"id":"HUTX","name":"Hutatma Sahakari Bank"},{"id":"HVBK","name":"Woori Bank"},{"id":"IBBK","name":"PT Bank Maybank Indonesia TBK"},{"id":"IBKL","name":"IDBI"},{"id":"IBKO","name":"Industrial Bank of Korea"},{"id":"ICBK","name":"Industrial and Commercial Bank of China"},{"id":"ICBL","name":"Industrial Co-operative Bank"},{"id":"ICHX","name":"Ichalkaranji Merchants Co-operative Bank"},{"id":"ICIC","name":"ICICI Bank"},{"id":"ICMX","name":"Indore Cloth Market Co-operative Bank"},{"id":"IDFB","name":"IDFC FIRST Bank"},{"id":"IDIB","name":"Indian Bank"},{"id":"IDUK","name":"Idukki District Co-operative Bank"},{"id":"IDUX","name":"Idukki District Co-operative Bank"},{"id":"IMPX","name":"Imphal Urban Co-operative Bank"},{"id":"INCX","name":"Indapur Urban Co-operative Bank"},{"id":"INDB","name":"Indusind Bank"},{"id":"INDX","name":"Independence Co-operative Bank"},{"id":"IOBA","name":"Indian Overseas Bank"},{"id":"IPOS","name":"India Post Payments Bank"},{"id":"IPPB","name":"India Post Payments Bank"},{"id":"IPCX","name":"Indore Premier Co-operative Bank Indore"},{"id":"IPSX","name":"Indore Paraspar Sahakari Bank"},{"id":"ISBX","name":"Indraprastha Sehkari Bank"},{"id":"ISMX","name":"Indore Swayam Mahila Co-operative Bank"},{"id":"ITBL","name":"Irinjalakuda Town Co-operative Bank"},{"id":"ITCX","name":"Irinjalakuda Town Co-operative Bank"},{"id":"ITDX","name":"Income Tax Dept Co-operative Bank"},{"id":"IUCB","name":"Integral Urban Co-operative Bank"},{"id":"IUCX","name":"Imperial Urban Co-operative Bank"},{"id":"JACX","name":"Jain Co-operative Bank"},{"id":"JAKA","name":"Jammu and Kashmir Bank"},{"id":"JALX","name":"Janalaxmi Co-operative Bank"},{"id":"JAMX","name":"Jamia Co-operative Bank"},{"id":"JANA","name":"Janaseva Sahakari Bank"},{"id":"JANX","name":"Janata Co-operative Bank"},{"id":"JASB","name":"Janaseva Sahakari Bank (Borivli)"},{"id":"JASX","name":"Janatha Seva Co-operative Bank"},{"id":"JAUX","name":"Jaihind Urban Co-op Bank"},{"id":"JBHX","name":"Jila Sahakari Kendriya Bank Maryadit Bhind"},{"id":"JBIX","name":"Jila Sahkari Kendriya Bank Maryadit Bilaspur"},{"id":"JBMX","name":"Jila Sahakari Kendriya Bank Maryadit Sagar"},{"id":"JCBX","name":"Janata Co-operative Bank Malegaon."},{"id":"JCCB","name":"Jaipur Central Co-operative Bank"},{"id":"JCCX","name":"Jalandhar Central Co-operative Bank"},{"id":"JCDX","name":"Jamnagar District Co-operative Bank"},{"id":"JCHX","name":"Jila Sahakari Kendriya Bank Mydt Chhatarpur"},{"id":"JCPX","name":"Janata Co Op Bank"},{"id":"JCUX","name":"Jagruti Co-operative Urban Bank"},{"id":"JDCX","name":"Jalaun District Co-operative Bank"},{"id":"JDEX","name":"Jila Sahakari Kendriya Bank Mydtt Dewas"},{"id":"JGBX","name":"Jharkand Gramin Bank"},{"id":"JGCX","name":"Jogindra Central Co-operative Bank"},{"id":"JGWX","name":"Jila Sahakari Bank Mydt. Gwalior"},{"id":"JHAX","name":"Jharneshwar Nagrik Sahakari Bank Maryadit"},{"id":"JHSX","name":"Jila Sahakari Kendriya Bank Mydt Hoshangabad"},{"id":"JHUX","name":"Jhunjhunu Kenddriya Sahakari Bak"},{"id":"JIBX","name":"Jila Sahakari Kendriya Bank Maryadit Balaghat"},{"id":"JICX","name":"Jila Sahakari Kendriya Bank Maryadit Chhindwara"},{"id":"JIDX","name":"Jila Sahkari Kendriya Bank Mydt Damoh"},{"id":"JIGX","name":"Jila Sahakari Kendriya Bank Mydt Guna"},{"id":"JIKX","name":"Jila Sahakari Kendariya Bank Mydt Khandwa"},{"id":"JIMX","name":"Jila Sahakari Kendriya Bank Mydt Mandla"},{"id":"JINX","name":"Jind Central Co-operative Bank"},{"id":"JIOP","name":"Jio Payments Bank"},{"id":"JIOX","name":"Jila Sahakari Kendriya Bank Mydt Shahdol"},{"id":"JIRX","name":"Jila Sahakari Kendriya Bank Maryadit Rajgarh"},{"id":"JISX","name":"Jila Sahakari Kendriya Bank Maryadit Sidhi"},{"id":"JIVX","name":"Jivaji Sahakari Bank  Ichalkaranji"},{"id":"JJCX","name":"Jhajjar Central Co-operative Bank"},{"id":"JJHX","name":"Jila Sahkari Kendriya Bank Mydt Jhabua"},{"id":"JJSB","name":"Jalgaon Janata Sahkari Bank"},{"id":"JKAX","name":"Jila Sahakari Kendriya Bank Mydt Ambikapur"},{"id":"JKCX","name":"Janakalyan Co-operative Bank Nashik"},{"id":"JKDX","name":"Jila Sahakari Kendriya Bank Mydt. Jabalpur"},{"id":"JKEX","name":"Jhalawar Kendriya Sahkari Bank"},{"id":"JKHX","name":"Jila Sahkari Kendriya Bank Maryadit Khargone"},{"id":"JKMX","name":"Jila Sahakari Kendriya Bank Maryadit Jagdalpur"},{"id":"JKRX","name":"Jilla Sahakari Kendriya Bank Mydt Raisen"},{"id":"JKSX","name":"J&k State Co-operative Bank"},{"id":"JLCX","name":"Jalore Central Co-operative Bank Jalore"},{"id":"JLDX","name":"Jalna District Central Co-operative Bank"},{"id":"JLNX","name":"Jalna Peoples Co-operative Bank Jalna"},{"id":"JLSX","name":"Jila Sahakari Kendriya Bank Mydt Vidisha"},{"id":"JLWX","name":"Jhalawar Nagrik Sahakari Bank"},{"id":"JMAX","name":"Jila Sahakari Kendriya Bank Mydt Mandsaur"},{"id":"JMBX","name":"Jila Sahakari Kendriya Bank Maryadit Betul"},{"id":"JMCX","name":"Jalna Merchants Co-operative Bank"},{"id":"JMDX","name":"Jila Sahkari Kendriya Bank Mydt Datia"},{"id":"JMHX","name":"Jamshedpur Urban Co-operative Bank"},{"id":"JMMX","name":"Jammu Central Co-operative Bank"},{"id":"JMOX","name":"Jila Sahakari Kendriya Bank Mydt Morena"},{"id":"JMPX","name":"Jamnagar Peoples Co-operative Bank"},{"id":"JMSX","name":"Jijamata Mahila Sahakari Bank"},{"id":"JMYX","name":"Jila Sahakari Kendriya Bank Mydt Durg"},{"id":"JNAX","name":"Jila Sahakari Kendriya Bank Mydt Narsinghpur"},{"id":"JNDX","name":"Junagadh Jilla Sahakari Bank"},{"id":"JNSX","name":"Janseva Nagari Sahakari Bank Marydit"},{"id":"JODX","name":"Jodhpur Central Co-operative Bank"},{"id":"JONX","name":"Jodhpur Nagrik Sahakari Bank"},{"id":"JOWX","name":"Jowai Co-operative Urban Bank"},{"id":"JPAX","name":"Jila Sahakari Kendriya Bank Mydt Panna"},{"id":"JPCB","name":"Jalgaon Peoples Co-operative Bank"},{"id":"JPCX","name":"Jalpaiguri Central Co-operative Bank"},{"id":"JRAX","name":"Jila Sahakari Kendriya Bank Mydt Ratlam"},{"id":"JRKX","name":"Jila Sahakari Kendriya Bank Mydt Ujjain"},{"id":"JRNX","name":"Jila Sahakari Kendriya Bank Maryadit Rajnandgaon"},{"id":"JRSX","name":"Jalore Nagrik Sahakari Bank"},{"id":"JSAB","name":"Jain Sahakari Bank"},{"id":"JSAX","name":"Janata Sahakari Bank Ajara"},{"id":"JSBL","name":"Janakalyan Sahakari Bank"},{"id":"JSBP","name":"Janata Sahakari Bank (Pune)"},{"id":"JSBX","name":"Janaseva Co-operative Bank (Nashik)"},{"id":"JSCX","name":"Jharkhand State Co-operative Bank"},{"id":"JSDX","name":"Jila Sahakari Kendriya Bank Mydt Dhar"},{"id":"JSEX","name":"Jila Sahakari Kendriya Bank Mydt Sehore"},{"id":"JSFB","name":"Jana Small Finance Bank"},{"id":"JSHX","name":"Jila Sahakari Kendriya Bank Mydt Shajapur"},{"id":"JSKX","name":"Jila Sahakari Kendriya Bank Maryadit Raipur"},{"id":"JSMX","name":"Janata Sahakari Bank Amravati"},{"id":"JSOX","name":"Jila Sahakari Kendriya Bank Myt Seoni"},{"id":"JSRX","name":"Jila Sahakari Kendriya Bank Mydt Rewa"},{"id":"JSTX","name":"Jila Sahakari Kendriya Bank Mydt Satna"},{"id":"JSVX","name":"Jila Sahakari Kendriya Bank Maryadit Shivpuri"},{"id":"JSWX","name":"Jansewa Urban Co-operative Bank"},{"id":"JTIX","name":"Jila Sahakari Kendriya Bank Mydt Tikamgarh"},{"id":"JTSX","name":"Jugalkishor Tapdiya Shree Mahesh Ucb Aurangabadltd"},{"id":"JUCX","name":"Junagadh Commercial Co-operative Bank"},{"id":"JUSX","name":"Jaysingpur Udgaon Sahakari Bank Jaysingpur"},{"id":"JVCX","name":"Jivan Commercial Co-operative Bank"},{"id":"KAAX","name":"Kadappa District Co-operative Central Bank"},{"id":"KACE","name":"Kangra Central Co-operative Bank"},{"id":"KACX","name":"Kachchh District Central Co-operative Bank"},{"id":"KADX","name":"Kasaragod District Co-operative Bank"},{"id":"KAGX","name":"Kagal Co-operative Bank Kagal"},{"id":"KAIJ","name":"Kallappanna Awade Ichalkaranji Janata Sahakari Bank"},{"id":"KALX","name":"Kalna Town Credit Co-operative Bank"},{"id":"KAMX","name":"Kamala Co-operative Bank Solapur"},{"id":"KANG","name":"Kangra Co-operative Bank"},{"id":"KANX","name":"Kanara District Central Co-operative Bank"},{"id":"KARB","name":"Karnataka Bank"},{"id":"KARX","name":"Kaira Dist Central Co-operative Bank"},{"id":"KASX","name":"Kashmir Mercantile Co-operative Bank"},{"id":"KATX","name":"Kattappana Urban Co-operative Bank"},{"id":"KAYX","name":"Kanyakumari District Central Co-operative Bank"},{"id":"KBCX","name":"Kanakamahalakshmi Co-operative Bank"},{"id":"KBNX","name":"Khambhat Nagarik Sahakari Bank"},{"id":"KBSX","name":"Krishna Bhima Samruddhi Local Area Bank"},{"id":"KCBL","name":"Kapol Co-operative Bank"},{"id":"KCBX","name":"Kutch Co-operative Bank"},{"id":"KCCB","name":"Kalupur Commercial Co-operative Bank"},{"id":"KCCX","name":"Kancheepuram Central Co-operative Bank"},{"id":"KCDX","name":"Karnatak Central Co-operative Bank Dharwad"},{"id":"KCEX","name":"Kota Central Co-operative Bank Kota"},{"id":"KCOB","name":"Kangra Co-operative Bank"},{"id":"KCUB","name":"Khattri Co-operative Urban Bank"},{"id":"KCUX","name":"Kannur Co-operative Urban Bank"},{"id":"KDBX","name":"Karimnagar District Co-operative Central Bank"},{"id":"KDCB","name":"Kozhikode District Co-operatiave Bank"},{"id":"KDCX","name":"Kozhikode District Co-operative Bank"},{"id":"KDIX","name":"Shree Kadi Nagarik Sahakari Bank"},{"id":"KDNX","name":"Kodinar Nagrik Sahakari Bank Limited,kodinar"},{"id":"KDUX","name":"Kodagu District Co-operative Central Bank"},{"id":"KEMX","name":"Kerala Mercantile Co-operative Bank"},{"id":"KESX","name":"Keshav Sehkari Bank"},{"id":"KGBX","name":"Kaveri Grameena Bank"},{"id":"KGDX","name":"Khagaria District Central Co-operative Bank"},{"id":"KGRB","name":"Kaveri Grameena Bank"},{"id":"KGSX","name":"Kashi Gomti Samyut Gramin Bank"},{"id":"KHAX","name":"Khalilabad Nagar Sahkari Bank"},{"id":"KHCX","name":"Khardah Co-operative Bank"},{"id":"KHDX","name":"Kheda People's Co-operative Bank"},{"id":"KHNX","name":"Kohinoor Sahakari Bank Ichalkaranji"},{"id":"KHUX","name":"Khamgaon Urban Co-operative Bank"},{"id":"KICX","name":"Kaithal Central Co-operative Bank"},{"id":"KJSB","name":"Kalyan Janata Sahakari Bank"},{"id":"KJSX","name":"Karad Janata Sahakari Bank"},{"id":"KKBK","name":"Kotak Mahindra Bank"},{"id":"KKMX","name":"Kankaria Mainagar Nagrik Sahakari Bank"},{"id":"KKSX","name":"Kumbhi Kasari Sahkari Bank Kuditre"},{"id":"KLGB","name":"Kerala Gramin Bank"},{"id":"KLMX","name":"Kollam District Co-operative Bank"},{"id":"KMCB","name":"Kokan Mercantile Co-operative Bank"},{"id":"KMCX","name":"Krishna Mercantile Co-operative Bank"},{"id":"KMNX","name":"Kota Mahila Nagrik Sahakari Bank"},{"id":"KMSX","name":"Kolhapur Mahila Sahakari Bank"},{"id":"KNBX","name":"Kalol Nagarik Sahakari Bank"},{"id":"KNCX","name":"Karnal Central Co-operative Bank"},{"id":"KNNX","name":"Sri Kannikaparameswari Co-operative Bank"},{"id":"KNPX","name":"Karnala Nagari Sahakari Bank Panvel"},{"id":"KNSB","name":"Kurla Nagarik Sahakari Bank"},{"id":"KNSX","name":"Kisan Nagari Sahakari Bank Maryadit Parbhani"},{"id":"KOBX","name":"Kopargaon Peoples Co-operative Bank"},{"id":"KOCX","name":"Konoklota Mahila Urban Co-operative Bank"},{"id":"KODX","name":"Kodungallur Town Co-operative Bank"},{"id":"KOEX","name":"KEB Hana Bank"},{"id":"KOSX","name":"Kota Nagrik Sahkari Bank Kota"},{"id":"KOTX","name":"Kodinar Taluka Co-operative Banking Union K"},{"id":"KOYX","name":"Koylanchal Urban Co-operative Bank"},{"id":"KPCX","name":"Kolhapur Dist.central Co-operative Bank Kolhapur"},{"id":"KRCX","name":"Kolar And Chickballapur Dt Co-operative Central Bank"},{"id":"KRDX","name":"Krishna District Co-operative Bank"},{"id":"KRIX","name":"Krishnagar City Co-operative Bank"},{"id":"KRMX","name":"Karamana Co-operative Urban Bank"},{"id":"KRNX","name":"Karnavati Co-operative Bank"},{"id":"KRTH","name":"Krungthai Bank"},{"id":"KRTX","name":"Kranthi Co-operative Urban Bank"},{"id":"KSBX","name":"Krishna Sahakari Bank Rethare Bk"},{"id":"KSCB","name":"Karnataka State Co-operative Apex Bank"},{"id":"KSCX","name":"Kerala State Co-operative Bank"},{"id":"KSMX","name":"Kosamba Mercantile Co-operative Bank"},{"id":"KSNX","name":"Koteshwara Sahakari Bank Niyamitha"},{"id":"KSTX","name":"Kasaragod Co-operative Town Bank No 970"},{"id":"KSUX","name":"Kashipur Urban Co-operative Bank"},{"id":"KTBX","name":"Kottayam District Co-operative Bank"},{"id":"KTCX","name":"Kapurthala Central Co-operative Bank"},{"id":"KTDX","name":"Katihar District Central Co-operative Bank"},{"id":"KTTX","name":"Tumkur District Central Bank"},{"id":"KUBX","name":"Kaduthuruthy Urban Co-operative Bank"},{"id":"KUCB","name":"Karad Urban Co-operative Bank"},{"id":"KUCX","name":"Kolhapur Urban Co-operative Bank"},{"id":"KUKX","name":"Kukarwada Nagarik Sahakari Bank"},{"id":"KULX","name":"Kodoli Urban Co-operative Bank Kodoli"},{"id":"KUMX","name":"Kumbakonam Central Co-operative Bank"},{"id":"KUNS","name":"Kurmanchal Nagar Sahkari Bank"},{"id":"KURX","name":"Kurukshetra Central Co-operative Bank"},{"id":"KYDX","name":"Kalaburagi and Yadgir Dist Co-operative Central Bank"},{"id":"KVBL","name":"Karur Vysya Bank"},{"id":"KVCX","name":"Kavita Urban Co-operative Bank"},{"id":"KVGB","name":"Karnataka Vikas Grameena Bank"},{"id":"LACX","name":"Laxmi Co-operative Bank Solapur"},{"id":"LATX","name":"Latur Urban Co-operative Bank Latur"},{"id":"LAVB","name":"Laxmi Vilas Bank"},{"id":"LBMX","name":"Laxmibai Mahila Nagrik Sahakari Bank Maradit"},{"id":"LCBX","name":"Lalbaug Co-operative Bank"},{"id":"LCCX","name":"Ludhiana Central Co-operative Bank"},{"id":"LDCX","name":"Latur District Central Co-operative Bank"},{"id":"LDPX","name":"Loknete Dattaji Patil Sahakari Bank"},{"id":"LDRX","name":"Langpi Dehangi Rural Bank"},{"id":"LECX","name":"Lic Employees Co-operative Bank,udupi"},{"id":"LICB","name":"Liluah Co-operative Bank"},{"id":"LKBL","name":"Lord Krishna Bank"},{"id":"LKCX","name":"Little Kancheepuram Co-operative Urban Bank"},{"id":"LKHX","name":"Lakhimpur Urban Co-operative Bank"},{"id":"LKMX","name":"Lokmangal Co-operative Bank Solapur"},{"id":"LMNX","name":"Laxmi Mahila Nagrik Sahakari Bank Maryadit"},{"id":"LNSX","name":"Lunawada Nagarik Sahakari Bank"},{"id":"LOKX","name":"Lokvikas Nagari Sahakari Bank Aurangabad"},{"id":"LONX","name":"Lonavala Sahakari Bank"},{"id":"LUCX","name":"Lucknow Urban Co-operative Bank"},{"id":"LULX","name":"Laxmi UrbanCo-operative Bank Latur"},{"id":"MABL","name":"Malleshwaram Co-operative Bank"},{"id":"MACX","name":"Mahabhairab Co-operative Urban Bank"},{"id":"MADX","name":"Madhyanchal Gramin Bank"},{"id":"MAGX","name":"Mewar Aanchalik Gramin Bank (merged With Rajasthan Marudhara Gramin Bank-mdgx)"},{"id":"MAHB","name":"Bank of Maharashtra"},{"id":"MAHG","name":"Maharashtra Gramin Bank"},{"id":"MAHX","name":"Shree Mahalaxmi Urban Co-operative Credit Bank"},{"id":"MAJX","name":"Manjeri Co-operative Urban Bank"},{"id":"MAKX","name":"Makarpura Industrial Estate Co-operative Bank"},{"id":"MALX","name":"Malviya Urban Co-operative Bank"},{"id":"MAMX","name":"Mandvi Mercantile Co-operative Bank"},{"id":"MANX","name":"Mansa Nagarik Sahakari Bank"},{"id":"MAPX","name":"Maharana Pratap Co-operative Urban Bank"},{"id":"MASX","name":"Mahesh Urban Co-operative Bank Solapur"},{"id":"MAUX","name":"Mantha Urban Co-operative Bank"},{"id":"MAVX","name":"Shree Mahavir Sahakari Bank"},{"id":"MAYX","name":"Mayani Urban Co-operative Bank"},{"id":"MBCX","name":"Mugberia Central Co-operative Bank"},{"id":"MBGX","name":"Madya Bihar Gramin Bank"},{"id":"MBLX","name":"Manmandir Co-operative Bank"},{"id":"MCAX","name":"Mahesh Urban Co-operative Bank Ahmedpur"},{"id":"MCBL","name":"Mahanagar Co-operative Bank"},{"id":"MCBX","name":"Modern Co-operative Bank"},{"id":"MCCX","name":"Muktsar Central Co-operativeerated Bank"},{"id":"MCDX","name":"Muzaffarnagar District Co-operative Bank"},{"id":"MCLX","name":"Mahendragarh Central Co-operative Bank"},{"id":"MCOX","name":"Mahesh Urban Co-operative Bank"},{"id":"MCSX","name":"Mattancherry Sarvajanik Co-operative Bank"},{"id":"MCUX","name":"Mahaveer Co-operative Urban Bank"},{"id":"MDCB","name":"Mumbai District Central Co-operative Bank"},{"id":"MDCX","name":"Madurai District Central Co-operative Bank"},{"id":"MDEX","name":"Model Co-operative Bank"},{"id":"MDGX","name":"Rajasthan Marudhara Gramin Bank"},{"id":"MDIX","name":"Mandya District Co-operative Central Bank"},{"id":"MDMX","name":"Mann Deshi Mahila Sahkari Bank"},{"id":"MDPX","name":"Md Pawar Peoples Co-operative Bank Urun Islampur"},{"id":"MEDX","name":"District Co-operative Central Bankmedak"},{"id":"MERX","name":"Meghalaya Rural Bank"},{"id":"MEUX","name":"Meenachil East Urban Co-operative Bank"},{"id":"MFCX","name":"Muzaffarpur Central Co-operative Bank"},{"id":"MFUX","name":"Mahatma Fule Urban Co-operative Bank,amravati"},{"id":"MGBX","name":"Maharashtra Gramin Bank"},{"id":"MGCB","name":"Mogaveera Co-operative Bank"},{"id":"MGCX","name":"Mansing Co-operative Bank"},{"id":"MGDX","name":"Magadh Central Co-operative Bank"},{"id":"MGRB","name":"Malwa Gramin Bank"},{"id":"MGSX","name":"Mangaldai Nagar Samabai Bank"},{"id":"MGUX","name":"Madgaum Urban Co-operative Bank"},{"id":"MHCB","name":"Mizuho Bank"},{"id":"MHCX","name":"Mahoba Urban Co-operative Bank Mahoba"},{"id":"MHEX","name":"Mahamedha Urban Co-operative Bank ( Under Rbi Direction)"},{"id":"MHLX","name":"Mahila Co-operative Bak"},{"id":"MHMX","name":"Shri Mahalaxmi Co-operative Bak Kolhapur"},{"id":"MHNX","name":"Mahanagar Nagrik Sahakari Bank Maryadit"},{"id":"MHSX","name":"Mahesh Sahakari Bank Pune"},{"id":"MHUX","name":"Mahesh Urbank Co-operative Bank Parli V."},{"id":"MIZX","name":"Mizoram Co-operative Apex Bank"},{"id":"MJCX","name":"Monghyr Jamui Central Co-operative Bank"},{"id":"MKUX","name":"Malkapur Urban Co-operative Bank"},{"id":"MKYX","name":"Marketyard Commercial Co-operativebank"},{"id":"MLDX","name":"Malda District Central Co-operative Bank"},{"id":"MMCX","name":"Mattancherry Mahajanik Co-operative Urban Bank"},{"id":"MMMX","name":"Mahila  Nagrik Sahakari Bank Maryadit Mahasamund"},{"id":"MNBX","name":"Mahila Co-operative Nagarik Bank,bharuch"},{"id":"MNCX","name":"Mansa Central Co-operative Bank"},{"id":"MNSX","name":"Mehsana Nagarik Sahakari Bank"},{"id":"MOGX","name":"Moga Central Co-operative Bank"},{"id":"MOUX","name":"Mohol Urban Co-operative Bank"},{"id":"MPCX","name":"Moirang Primary Co-operative Bank"},{"id":"MPDX","name":"Malappuram District Co-operative Bank"},{"id":"MPRX","name":"Madhtya Pradesh Rajya Sahakari Bank Maryadit"},{"id":"MRBX","name":"Manipur Rural Bank"},{"id":"MRTX","name":"Maratha Co-operative Bank"},{"id":"MSAX","name":"Mansarovar Urban Co-operative Bank"},{"id":"MSBL","name":"Malad Sahakari Bank"},{"id":"MSBX","name":"M.s.Co-operative Bank"},{"id":"MSCI","name":"Maharashtra State Co-operative Bank"},{"id":"MSCX","name":"Manipur State Co-operative Bank"},{"id":"MSHQ","name":"Mashreq Bank"},{"id":"MSNU","name":"Mehsana Urban Co-operative Bank"},{"id":"MSNX","name":"Mehsana District Central Co-operative Bank"},{"id":"MSOX","name":"Manorama Co-operative Bank Solapur"},{"id":"MSSX","name":"Merchants Souharda Sahakara Bank Niyamita"},{"id":"MUBL","name":"Municipal Co-operative Bank"},{"id":"MUBX","name":"Maharaja Co-operative Urban Bank"},{"id":"MUCX","name":"Mapusa Urban Co-operative Bank of Goa"},{"id":"MUDX","name":"Madheshwari Urban Development Co-operative Bank"},{"id":"MUNX","name":"Mahudha Nagarik Sahakari Bank"},{"id":"MUPX","name":"Mehmadabad Urban Peoples Co-operative Bank"},{"id":"MURX","name":"Murshidabad District Central Co-operative Bank"},{"id":"MUSX","name":"Muslim Co-operative Bank"},{"id":"MVCB","name":"Sir M Visvesvaraya Co-operative Bank"},{"id":"MVCX","name":"Mahaveer Co-operative Bank"},{"id":"MVIX","name":"Manvi Pattana Souharda Sahakari Bank Ni"},{"id":"MYAX","name":"Meghalaya Co-operative Apex Bank"},{"id":"MYSX","name":"Mysore Chamarajanagar District Co-operative Bank"},{"id":"MZCX","name":"Mizoram Urban Co-operative Development Bank"},{"id":"MZRX","name":"Mizoram Rural Bank"},{"id":"NABX","name":"Nandani Sahakari Bank Nandani"},{"id":"NACX","name":"Nalanda Central Co-operative Bank Nalanda"},{"id":"NAGX","name":"Nagaland Rural Bank"},{"id":"NAIX","name":"Nainital District Co-operative Bank"},{"id":"NALX","name":"National Urban Co-operative Bank"},{"id":"NANX","name":"Nanded District Central Co-operative Bank"},{"id":"NASX","name":"Nasik District Central Co-operative Bank"},{"id":"NATA","name":"National Australia Bank"},{"id":"NAUX","name":"Nagaur Central Co-operative Bank"},{"id":"NAVX","name":"Navnirman Co-operative Bank"},{"id":"NAWX","name":"Nawanagar Co-operative Bank"},{"id":"NBAD","name":"National Bank of Abu Dhabi PJSC"},{"id":"NBBX","name":"National Co-operative Bank Bangalore"},{"id":"NBCX","name":"Nalbari Urban Co-operative Bank"},{"id":"NBMX","name":"Nagrik Sahakari Bank, Vidisha"},{"id":"NBRD","name":"National Bank for Agriculture and Development"},{"id":"NCBL","name":"National Co-operative Bank"},{"id":"NCBX","name":"Nawanshahr Central Co-operative Bank"},{"id":"NCCX","name":"Nabadwip Co-operative Credit Bank"},{"id":"NCOX","name":"Nagnath Urban Co-operative Bank Hingoli"},{"id":"NCUX","name":"Nilambur Co-operative Urban Bank"},{"id":"NDCB","name":"Naval Dockyard Co-operative BANK"},{"id":"NDCX","name":"Nilgiris District Central Co-operative Bank"},{"id":"NDDX","name":"Nadia District Central Co-operative Bank"},{"id":"NDGX","name":"Nashik District Girna Sahakari Bank( Under Rbi Direction)"},{"id":"NDIX","name":"Nashik District Industrial & Mercantile Co-operative Bank"},{"id":"NESF","name":"North East Small Finance Bank"},{"id":"NEYX","name":"Neyyattinkara Co-operative Urban Bank"},{"id":"NGBX","name":"Nagar Sahakari Bank Maharajganj"},{"id":"NGKX","name":"Nagrik Sahakari Bank Maryadit Gwalior"},{"id":"NGNX","name":"Nagina Urban Co-operative Bank"},{"id":"NGRX","name":"Nagar Sahkari Bank"},{"id":"NGSB","name":"Nagpur Nagarik Sahakari Bank"},{"id":"NGSX","name":"Nagarik Sahakari Bank Maryadit Durg"},{"id":"NICB","name":"New India Co-operative Bank"},{"id":"NIDX","name":"Nidhi Co-operative Bank"},{"id":"NILX","name":"Nilkanth Co-operative Bank"},{"id":"NIRX","name":"Nirmal Urban Co-operative Bank Nagpur"},{"id":"NIUX","name":"Nileshwar Co-operative Urban Bank"},{"id":"NJCX","name":"Nav Jeevan Co-operative Bank"},{"id":"NJGX","name":"Narmada Jhabua Gramin Bank"},{"id":"NJMX","name":"Nashik Jillha Mahila Vikas Sahakari Bank"},{"id":"NJSX","name":"Nasik Jilha Mahila Sahakari Bank"},{"id":"NKGS","name":"NKGSB Co-operative Bank"},{"id":"NLGX","name":"Nalgonda Dist. Co-operative Central Bank"},{"id":"NLUX","name":"National Urban Co-operative Bank,bahraich"},{"id":"NMCB","name":"Nasik Merchants Co-operative Bank"},{"id":"NMCX","name":"Navi Mumbai Co-operative Bank"},{"id":"NMGB","name":"North Malabar Gramin Bank"},{"id":"NNCX","name":"Naroda Nagrik Co-operative Bank"},{"id":"NNSB","name":"Nutan Nagarik Sahakari Bank"},{"id":"NNSX","name":"Nutan Nagari Sahakari Bank Ichalkaranji"},{"id":"NOBX","name":"Noble Co-operative Bank"},{"id":"NOIX","name":"Noida Commercial Co-operative Bak"},{"id":"NOSC","name":"Bank of Nova Scotia"},{"id":"NPCX","name":"Nadiad Peoples Co-operative Bank"},{"id":"NPKX","name":"Nashik Zilha Sarkari & Parishad Karmachari Sb Nmt"},{"id":"NRDX","name":"Nasik Road Deolali Vyapari Sahakari Bank"},{"id":"NSBB","name":"Nagarik Sahakari Bank Bhiwandi"},{"id":"NSBX","name":"Nagrik Sahakari Bank Lucknow"},{"id":"NSCX","name":"Nagaland State Co-operative Bank"},{"id":"NSGX","name":"Nagar Sahakari Bank Gorakhpur"},{"id":"NSIX","name":"Nagrik Sahakari Bank Indore"},{"id":"NSJX","name":"Nagarik Sahakari Bank Maryadit,jagdalpur"},{"id":"NSMX","name":"Nagarik Samabay Bank"},{"id":"NSPB","name":"NSDL Payments Bank"},{"id":"NSPX","name":"Nishigandha Sahakari Bankpandharpur"},{"id":"NSRX","name":"Nagrik Sahakari Bank"},{"id":"NTBL","name":"Nainital Bank"},{"id":"NUBX","name":"New Urban Co-operative Bank Rampur"},{"id":"NUCB","name":"Nagar Urban Co-operative Bank"},{"id":"NUCX","name":"Navabharat Co-operative Urban Bank"},{"id":"NVCX","name":"Navanagara Urban Co-operative Bank"},{"id":"NVNM","name":"Navnirman Co-operative Bank"},{"id":"NVSX","name":"Nagar Vikas Sahkari Bank"},{"id":"NWCX","name":"Nawada Central Co-operative Bank"},{"id":"ODCX","name":"Osmanabad District Central Co-operative Bank"},{"id":"ODGB","name":"Odisha Gramya Bank"},{"id":"OIBA","name":"HSBC Bank Oman S.A.O.G"},{"id":"OMCX","name":"Ojhar Merchant's Co-operative Bank"},{"id":"ONSX","name":"Omkar Nagreeya Sahkari Bank"},{"id":"ORBC","name":"Oriental Bank of Commerce"},{"id":"ORCB","name":"Odisha State Co-operative Bank"},{"id":"OSMX","name":"Osmanabad Janata Sahakari Bank"},{"id":"PABX","name":"Pallavan Grama Bank"},{"id":"PACX","name":"Pali Central Co-operative Bank"},{"id":"PADX","name":"Padra Nagar Nagrik Sahakari Bank"},{"id":"PALX","name":"Pali Urban Co-operative Bank"},{"id":"PANX","name":"Panchmahal District Co-operative Bank"},{"id":"PARX","name":"Parbhani District Central Co-operative Bank"},{"id":"PASX","name":"Paschim Banga Gramin Bank"},{"id":"PATX","name":"Pathanmthitta District Co-operative Bank"},{"id":"PAYX","name":"Payangadi Urban Co-operative Bank"},{"id":"PBGX","name":"Puduvai Bharathiar Grama Bank"},{"id":"PCBL","name":"Patan Co-operativeeartive Bank"},{"id":"PCBX","name":"Parshwanath Co-operative Bank"},{"id":"PCCX","name":"Panchkula Central Co-operative Bank"},{"id":"PCLX","name":"Pragathi Co-operative Bank, Bangalore"},{"id":"PCMX","name":"Panchsheel Mercantile Co-operative Bank"},{"id":"PCOX","name":"Peoples' Co-operative Bank"},{"id":"PCPX","name":"Pimpri Chinchwad Sahakari Bank Maryadit,pimpri"},{"id":"PCSX","name":"Pondicherry State Co-operative Bank"},{"id":"PCTX","name":"Pune Cantonment Sahakari Bank"},{"id":"PCUX","name":"Pochampally Co-operative Urban Bank"},{"id":"PDBX","name":"Purnea District Central Co-operative Bank"},{"id":"PDCX","name":"Pune District Central Co-operative Bank"},{"id":"PDNX","name":"Pandyan Grama Bank"},{"id":"PDSX","name":"Priyadarshani Nagari Sahakari Bank Jalna."},{"id":"PDUX","name":"Pandharpur Urban Co-operative Bank"},{"id":"PGBX","name":"Pragathi Krishna Gramin Bank"},{"id":"PGCX","name":"Progressive Co-operative Bank"},{"id":"PGRX","name":"Progressive Urban Co-operative Bank"},{"id":"PGTX","name":"Pragati Co-operative Bank,thara"},{"id":"PITX","name":"Pithoragarh Zila Sahkari Bank"},{"id":"PJSB","name":"Gopinath Patil Parsik Janata Sahakari Bank"},{"id":"PKBX","name":"Panchkula Urban Co-operative Bank Lmited"},{"id":"PKDX","name":"Palakkad District Co-operative Bank"},{"id":"PKGB","name":"Pragathi Krishna Gramin Bank"},{"id":"PLOX","name":"Palamoor Co-operative Urban Bank"},{"id":"PLUX","name":"Palus Sahakari Bank"},{"id":"PMCB","name":"Punjab & Maharashtra Co-operative Bank"},{"id":"PMCX","name":"Pimpalgaon Merchants Co-operative Bank"},{"id":"PMEC","name":"Prime Co-operative Bank"},{"id":"PMNX","name":"Pragati Mahila Nagrik Sahakari Bank Bhilai"},{"id":"PNCX","name":"Panipat Urban Co-operative Bank"},{"id":"PNMX","name":"Pune Merchant's Co-operative Bank"},{"id":"PNPX","name":"Panipat Central Co-operative Bank"},{"id":"PNSX","name":"Poornawadi Nagrik Sahakari Bank"},{"id":"PPBX","name":"Pune People's Co-operative Bank"},{"id":"PPCX","name":"Pachora Peoples Co-operative Bankpachora"},{"id":"PRCX","name":"Proddatur Co-operative Town Bank"},{"id":"PREX","name":"Prerana Co-operative Bank"},{"id":"PROX","name":"Progressive Mercantile Co-operative Bank"},{"id":"PRPX","name":"Paraspar Sahayak Co-operative Bank"},{"id":"PRSX","name":"Pravara Sahakari Bank"},{"id":"PRTH","name":"Prathama Bank"},{"id":"PSBX","name":"Pragati Sahakari Bank"},{"id":"PSCX","name":"Punjab State Co-operative Bank"},{"id":"PSIB","name":"Punjab & Sind Bank"},{"id":"PSRX","name":"Sri Potti Sriramulu Nellore Dccb"},{"id":"PSSX","name":"Prathamik Shikshak Sahakari Bank"},{"id":"PTCX","name":"Patiala Central Co-operative Bank"},{"id":"PTNX","name":"Patan Urban Co-operative Bank Patan"},{"id":"PTSX","name":"Patan Nagarik Sahakari Bank"},{"id":"PUBX","name":"Peoples Urban Co-operative Bank"},{"id":"PUCB","name":"Pandharpur Urban Co Op. Bank Pandharpur"},{"id":"PUCX","name":"Pusad Urban Co-operative Bank"},{"id":"PUDX","name":"Pudukottai District Central Co-operative Bank"},{"id":"PUGX","name":"Punjab Gramin Bank"},{"id":"PUNB","name":"Punjab National Bank"},{"id":"PUNX","name":"Pune Urban Co-operative Bank"},{"id":"PURX","name":"Purvanchal Gramin Bank"},{"id":"PUSX","name":"Purasawalkam Co-operative Bank"},{"id":"PUUX","name":"Puri Urban Co-operative Bank"},{"id":"PVAX","name":"Pavana Sahakari Bank"},{"id":"PVCX","name":"Purvanchal Co-operative Bank Gazipur"},{"id":"PVVX","name":"Padmashri Dr. Vitthalrao Vikhe Patil Co-operative Bank"},{"id":"PWUX","name":"Parwanoo Urban Co-operative Bank"},{"id":"PYCX","name":"Payyoli Co-operative Urban Bank"},{"id":"PYTM","name":"Paytm Payments Bank"},{"id":"QNBA","name":"Qatar National Bank Saq"},{"id":"QUCX","name":"Quilon Co-operative Urban Bank"},{"id":"RABO","name":"Rabobank International"},{"id":"RACX","name":"Rajkot Commercial Co-operative Bank"},{"id":"RAEX","name":"Railway Employees Co-operative Bank"},{"id":"RAJX","name":"Rajsamand Urban Co-operative Bank"},{"id":"RAKX","name":"Rajkot Peoples Co-operative Bank"},{"id":"RAMX","name":"Rajputana Mahila Urban Co-operative Bak"},{"id":"RANX","name":"Rander Peoples Co-operative Bank"},{"id":"RATN","name":"RBL Bank"},{"id":"RAUX","name":"Rajlaxmi Urban Co-operative Bank"},{"id":"RBBX","name":"Rajarambapu Sahakari Bank Peth"},{"id":"RBCX","name":"Reserve Bank Employees Co-operative Bank"},{"id":"RBIS","name":"Reserve Bank of India"},{"id":"RBIH","name":"IDRBT"},{"id":"RCBX","name":"Raniganj Co-operative Bank"},{"id":"RCCX","name":"Ropar Central Co-operative Bank"},{"id":"RCDX","name":"Ramanathapuram District Central Co-operative Bank"},{"id":"RCMX","name":"Ravi Commercial Urban Co-operative Bank"},{"id":"RCUX","name":"Rajadhani Co-operative Urban Bank"},{"id":"RDCX","name":"Raigad District Central Co-operative Bank"},{"id":"RDNX","name":"Col Rd Nikam Sainik Sahakari Bank"},{"id":"REBX","name":"Rendal Sahakari Bank Rendal"},{"id":"RECX","name":"Railway Employees Co-operative Banking Society"},{"id":"REWX","name":"Rewari Central Co-operative Bank"},{"id":"RGCX","name":"Ramgarhia Co-operative Bank"},{"id":"RGSX","name":"Rajgurunagar Sahakari Bank"},{"id":"RHMX","name":"Raj Laxmi Mahila Urban Co-operative Bank Jaipur"},{"id":"RJCX","name":"Raiganj Central Co-operative Bank"},{"id":"RJJX","name":"Rajajinagar Co-operative Bank"},{"id":"RJNX","name":"Rajpipla Nagarik Sahakari Bank"},{"id":"RJTX","name":"Shri Rajkot District Co-operative Bank"},{"id":"RKCX","name":"Ranchi Khunti Central Co-operative Bank"},{"id":"RLUX","name":"Ranilaxmibai Urban Co-operative Bank"},{"id":"RNBX","name":"Ranuj Nagrik Sahakari Bank"},{"id":"RNDX","name":"Ratnagiri District Central Co-operative Bank"},{"id":"RNGX","name":"Ranga Reddy Co-operative Urban Bank"},{"id":"RNSB","name":"Rajkot Nagarik Sahakari Bank"},{"id":"RNSX","name":"Rajdhani Nagar Sahkari Bank"},{"id":"ROCX","name":"Rohika Central Co-operative Bank Madhubani"},{"id":"ROHX","name":"Rohtak Central Co-operative Bank"},{"id":"RPUX","name":"Rajapur Urban Co-operative Bank"},{"id":"RRBP","name":"Rajarambapu Sahakari Bank"},{"id":"RRSX","name":"Ramrajya Sahakari Bank"},{"id":"RSBL","name":"Rajgurunagar Sahakari Bank"},{"id":"RSBX","name":"Raigad Sahakari Bank"},{"id":"RSCB","name":"Rajasthan State Co-operative Bank"},{"id":"RSSX","name":"Rajarshi Shahu Sahakari Bank"},{"id":"RSUX","name":"Radhasoami Urban Co-operative Bank"},{"id":"RSVX","name":"Rajarshi Shahu Govt Servants Co-operative Bank Kolh"},{"id":"RUCX","name":"Rajasthan Urban Co-operative Bank"},{"id":"RUKX","name":"Shri Rukmini Sahakari Bank"},{"id":"RUMX","name":"Raipur Urban Mercantile Co-operative Bank"},{"id":"RZSX","name":"Rampur Zila Sahkari Bank"},{"id":"SABR","name":"SBER Bank"},{"id":"SABX","name":"Saraswati Sahakari Bank"},{"id":"SACB","name":"Shri Arihant Co-operative Bank"},{"id":"SACX","name":"Sarvodaya Co-operative Bank Mumbai"},{"id":"SADX","name":"Sabarkantha District Central Co-operative Bank"},{"id":"SAGX","name":"Saurashtra Gramin Bank"},{"id":"SAHE","name":"Sahebrao Deshmukh Co-operative Bank"},{"id":"SAHX","name":"Sadhana Sahakari Bank Pune"},{"id":"SAIX","name":"Sanmitra Sahakari Bank"},{"id":"SALX","name":"Salal Sarvodaya Nagarik Sahakari Bank"},{"id":"SAMX","name":"Samata Sahakari Bank"},{"id":"SANX","name":"Saibaba Nagari Sahakari Bank"},{"id":"SAPX","name":"Shrimant Malojiraje Sahakari Bank"},{"id":"SARX","name":"Sardarganj Mercantile Co-operative Bank"},{"id":"SASA","name":"Sahyadri Sahakari Bank"},{"id":"SASX","name":"S.a.s Nagar Central Co-operative Bank"},{"id":"SATX","name":"Adv.shamraoji Shinde Satyashodhak Bank"},{"id":"SAUX","name":"Saidapet Co-operative Urban Bank"},{"id":"SAVX","name":"Sardar Vallabhbhai Sahakari Bank"},{"id":"SAWX","name":"Sawai Madhopur Kendriya Sahakari Bank"},{"id":"SBBJ","name":"State Bank of Bikaner and Jaipur"},{"id":"SBCX","name":"Sultan's Battery Co-operative Urban Bank"},{"id":"SBHY","name":"State Bank of Hyderabad"},{"id":"SBIN","name":"State Bank of India"},{"id":"SBKX","name":"Sri Channabasavaswamy Souhardha Pattana Sahak Bank"},{"id":"SBLD","name":"Sonali Bank"},{"id":"SBLS","name":"Samarth Sahakari Bank"},{"id":"SBLX","name":"Shubhalakshmi Mahila Co-operative Bank"},{"id":"SBMX","name":"Sri Banashankari Mahila Co-operative Bank"},{"id":"SBMY","name":"State Bank of Mysore"},{"id":"SBNX","name":"Shree Bhavnagar Nagrik Sahakari Bank"},{"id":"SBPX","name":"Sardar Bhiladwala Pardi People's Co-operative Bank"},{"id":"SBSX","name":"Shivajirao Bhosale Sahakari Bank"},{"id":"SBTR","name":"State Bank of Travancore"},{"id":"SBUJ","name":"Shri Bharat Urban Co-operative Bank Jaysingpur"},{"id":"SBUX","name":"Shree Balaji Urban Co-operative Bank"},{"id":"SCBL","name":"Standard Chartered Bank"},{"id":"SCBX","name":"Sirohi Central Co-operative Bank"},{"id":"SCCX","name":"Salem District Central Co-operative Bank"},{"id":"SCDX","name":"South Canara District Central Co-operative Bank"},{"id":"SCIX","name":"Social Co-operative Bank"},{"id":"SCNX","name":"Shri Chhani Nagrik Sahkari Bank"},{"id":"SCOB","name":"Samruddhi Co-operative Bank"},{"id":"SCOX","name":"Shimoga District Co-operative Central Bank"},{"id":"SCPX","name":"Sangrur Central Co-operative Bank"},{"id":"SCSX","name":"Sree Charan Souhardha Co-operative Bank"},{"id":"SCUX","name":"Sudha Co-operative Urban Bank"},{"id":"SDBX","name":"Samata Co-operative Development Bank"},{"id":"SDCB","name":"Surat District Co-operative Bank"},{"id":"SDCX","name":"Sindhudurg  District Central Co-operative Bank"},{"id":"SDHX","name":"Solapur Siddheshwar Sahakari Bank"},{"id":"SDSX","name":"Satara District Central Co-operative Bank"},{"id":"SDTX","name":"Sambalpur District Co-operative Central Bank"},{"id":"SDUX","name":"Sri Sudha Co-operative Bank"},{"id":"SEMX","name":"Secunderabad Mercantile Co-operative Urban Bank"},{"id":"SENX","name":"Sehore Nagrik Sahakari Bank Sehore"},{"id":"SEUX","name":"Sevalia Urban Co-operative Bank"},{"id":"SEWX","name":"Shri Mahila Sewa Sahakari Bank"},{"id":"SGCX","name":"Sangli District Central Co-operative Bank"},{"id":"SGLX","name":"Sangli Sahakari Bank"},{"id":"SGSX","name":"Sadguru Nagrik Sahakari Bank Maryadit"},{"id":"SGUX","name":"Sadguru Gahininath Urban Co-operative Bank Akluj"},{"id":"SHAX","name":"Shankar Nagari Sahakari Bank"},{"id":"SHBK","name":"Shinhan Bank"},{"id":"SHBX","name":"Shriram Urban Co-operative Bank"},{"id":"SHCX","name":"Shimla Urban Co-operative Bank"},{"id":"SHEX","name":"Shree Samarth Sahakari Bank Nashik"},{"id":"SHGX","name":"Shri Ganesh Sahakari Bank"},{"id":"SHIX","name":"Shivalik Mercantile Co-operative Bank"},{"id":"SHKX","name":"Shikshak Sahakari Bank"},{"id":"SHMX","name":"Sanghamitra Co-operative Urban Bank"},{"id":"SHNX","name":"Shri Kanyaka Nagari Sahakari Bank"},{"id":"SHOX","name":"Sihor Mercantile Co-operative Bank"},{"id":"SHRX","name":"Shree Mahesh Co-operative Bank Nashik"},{"id":"SHSX","name":"Sharad Sahakari Bank"},{"id":"SHUX","name":"Shushruti Souharda Sahakara Bank Niyamita"},{"id":"SIBL","name":"South Indian Bank"},{"id":"SIBX","name":"Sikar Kendriya Sahakari Bank"},{"id":"SICX","name":"Sirsa Central Co-operative Bank"},{"id":"SIDB","name":"Small Industries Development Bank Of India"},{"id":"SIDC","name":"The Sindhudurg District Central Co-operative Bank"},{"id":"SIDX","name":"Siddhi Co-operative Bank"},{"id":"SIGX","name":"Singhbhum District Central Co-operative Bank"},{"id":"SIHX","name":"Sihor Nagarik Sahakari Bank"},{"id":"SIKX","name":"Sikar Urban Co-operative Bank"},{"id":"SINX","name":"Shihori Nagarik Sahakari Bank"},{"id":"SIRX","name":"Sircilla Co-operative Urban Bank"},{"id":"SISX","name":"Sanmati Sahakari Bank"},{"id":"SITX","name":"Sitamarhi Central Co-operative Bank"},{"id":"SIWX","name":"Siwan Central Co-operative Bank"},{"id":"SJGX","name":"Sutlej Gramin Bank"},{"id":"SJSB","name":"Solapur Janata Sahakari Bank"},{"id":"SJSX","name":"Solapur Janata Sahakari Bank"},{"id":"SKCX","name":"Shrikrishna Co-operative Bank"},{"id":"SKKX","name":"Sikkim State Co-operative Bank"},{"id":"SKNX","name":"Sankheda Nagarik Sahakari Bank"},{"id":"SKSB","name":"Shikshak Sahakari Bank"},{"id":"SKUX","name":"S S L S A Kurundwad Urban Bank"},{"id":"SLAX","name":"Subhadra Local Area Bank"},{"id":"SLCX","name":"Shree Laxmi Co-operative Bank"},{"id":"SMBC","name":"Sumitomo Mitsui Banking Corporation"},{"id":"SMBX","name":"Sampada Sahakari Bank"},{"id":"SMCB","name":"Shivalik Mercantile Co-operative Bank"},{"id":"SMCX","name":"Sangamner Merchants Co-operative Bank"},{"id":"SMEX","name":"Sumerpur Mercantile Urban Co-operative Bank"},{"id":"SMMX","name":"Shree Mahalaxmi Mercantile Co-operative Bank"},{"id":"SMNX","name":"Shree Mahuva Nagrik Sahakari Bank"},{"id":"SMPX","name":"Shankarrao Mohite Patil Sahakri Bank"},{"id":"SMSX","name":"Soubhagya Mahila Souhardha Sahakari Bank"},{"id":"SMTX","name":"Sanmitra Urban Co-operative Bank"},{"id":"SMUX","name":"Shri Mahavir Urban Co-operative Bank"},{"id":"SMVC","name":"Sir M Visvesvaraya Co-operative Bank"},{"id":"SMWX","name":"Sree Subramanyeswara Co-operative Bank"},{"id":"SNAX","name":"Saraspur Nagarik Co-operative Bank"},{"id":"SNBX","name":"Sarvodaya Nagrik Sahkari Bank"},{"id":"SNCX","name":"Sonepat Urban Co-operative Bank"},{"id":"SNDX","name":"Sind Co-operative Urban Bank"},{"id":"SNGX","name":"Sarangpur Co-operative Bank"},{"id":"SNKX","name":"Shramik Nagrik Sahkari Bank"},{"id":"SNLX","name":"Sarjeraodada Naik Shirala Sahakari Bank"},{"id":"SNPX","name":"Sonepat Central Co-operative Bank"},{"id":"SNSV","name":"Sarakari Naukarara Sahakari Bank Niyamt Vijayapura"},{"id":"SNSX","name":"Smriti Nagrik Sahakari Bank"},{"id":"SOBX","name":"Secunderabad Co-operative Urban Bank"},{"id":"SOGE","name":"Societe Generale"},{"id":"SOLX","name":"Solapur District Central Co-operative Bank"},{"id":"SONX","name":"Sonbhadra Nagar Sahkari Bank"},{"id":"SPBX","name":"Saptagiri Grameena Bank"},{"id":"SPCB","name":"Surat People's Co-operative Bank"},{"id":"SPCX","name":"Shirpur Peoples Co-operative Bank"},{"id":"SPNX","name":"Shree Panchganga Nagari Sahakari Bank"},{"id":"SPSX","name":"Sandur Pattana Souharda Sahakari Bank Niyamitha"},{"id":"SPTX","name":"Shripatraodada Sahakari Bank"},{"id":"SRCB","name":"Saraswat Co-operative Bank"},{"id":"SRCX","name":"Shree Bharat Co-operative Bank"},{"id":"SREX","name":"Shree Co-operative Bank"},{"id":"SRGX","name":"Sree Narayana Guru Co-operative Bank"},{"id":"SRHX","name":"Shree Dharati Co-operative Bank"},{"id":"SRSX","name":"Sharad Nagari Sahakari Bank"},{"id":"SSBL","name":"Satara Shakari Bank"},{"id":"SSBX","name":"Shivdaulat Sahakari Bank"},{"id":"SSDX","name":"Suco Souharda Sahakari Bank"},{"id":"SSHX","name":"Shree Sharada Sahakari Bank"},{"id":"SSKX","name":"Sadhana Sahakari Bank"},{"id":"SSLX","name":"Solapur Social Urban Co-operative Bank"},{"id":"SSNX","name":"Sreenidhi Souharda Sahakari Bank Niyamitha"},{"id":"SSOX","name":"Samarth Sahakari Bank"},{"id":"SSSX","name":"Sant Sopankaka Sahakari Bank"},{"id":"SSWX","name":"Sundarlal Sawaji Urban Co-operative Bank"},{"id":"STBP","name":"State Bank of Patiala"},{"id":"STCB","name":"State Bank of Mauritius"},{"id":"STCX","name":"State Transport Co-operative Bank"},{"id":"STDX","name":"Samastipur District Central Co-operative Bank"},{"id":"STRX","name":"Sterling Urban Co-operative Bank"},{"id":"SUBX","name":"Sarva Up Gramin Bank"},{"id":"SUCX","name":"Sangli Urban Co-operative Bank"},{"id":"SUDX","name":"Surendranagar District Co-operative Bank"},{"id":"SULX","name":"Sulaimani Co-operative Bank"},{"id":"SUMX","name":"Surat Mercantile Co-operative Bank"},{"id":"SUNB","name":"Surat National Co-operative Bank"},{"id":"SURX","name":"Siddheshwar Urban Co-operative Bank Maryadit Sillod"},{"id":"SURY","name":"Suryoday Small Finance Bank"},{"id":"SUSX","name":"Sirsi Urban Sahakari Bank"},{"id":"SUTB","name":"Sutex Co-operative Bank"},{"id":"SUVX","name":"Suvarnayug Sahakari Bank"},{"id":"SVAX","name":"Sri Vasavamba Co-operative Bank"},{"id":"SVBL","name":"Seva Vikas Co-operative Bank"},{"id":"SVCB","name":"Shamrao Vithal Co-operative Bank"},{"id":"SVCX","name":"Sarvodaya Commerical Co-operative Bank"},{"id":"SVGX","name":"Sivagangai District Central Co-operative Bank"},{"id":"SVNX","name":"Shivaji Nagari Sahakari Bank"},{"id":"SVOX","name":"Sarvodaya Sahakari Bank"},{"id":"SVRX","name":"Shree Vardhaman Sahakari Bank"},{"id":"SVSH","name":"Shree Veershaiv Co-operative Bank"},{"id":"SVSX","name":"Shri Vinayak Sahakari Bank"},{"id":"SWMX","name":"Sawai Madhopur Urban Co-operative Bank"},{"id":"SWSX","name":"Shree Warana Sahakari Bank"},{"id":"SYNB","name":"Syndicate Bank"},{"id":"TACX","name":"Adinath Co-operative Bank"},{"id":"TADX","name":"Anantapur District Co-operative Central Bank"},{"id":"TAMX","name":"Anand Mercantile Co-operative Bank"},{"id":"TAPX","name":"Tapindu Urban Co-operative Bank"},{"id":"TASX","name":"Annasaheb Savant Co-operative Urban Bank Mahad"},{"id":"TBCX","name":"Bharath Co-operative Bank"},{"id":"TBDX","name":"Buldana District Central Co-operative Bank"},{"id":"TBHX","name":"Bhadran People's Co-operative Bank"},{"id":"TBMX","name":"Bapunagar Mahila Co-operative Bank"},{"id":"TBPX","name":"Botad Peoples Co-operative Bank"},{"id":"TBSB","name":"Thane Bharat Sahakari Bank"},{"id":"TBSX","name":"Bihar State Co-operative Bank"},{"id":"TBTX","name":"Baroda Traders Co-operative Bank"},{"id":"TBUX","name":"Balusseri Co-operative Urban Bank"},{"id":"TCBX","name":"Co-operative Bank of Rajkot"},{"id":"TCCX","name":"Commercial Co-operative Bank"},{"id":"TCHX","name":"Town Co-operative Bank Hoskote"},{"id":"TCPX","name":"Tamilnadu Circle Postal Co-operative Bank"},{"id":"TCUB","name":"Trivandrum Co-operative Urban Bank"},{"id":"TCUX","name":"Tiruvallur Co-operative Urban Bank"},{"id":"TDBX","name":"District Co-operative Central Bank"},{"id":"TDCB","name":"Thane District Central Co-operative Bank"},{"id":"TDCX","name":"Thrissur District Co-operative Bank"},{"id":"TDIX","name":"District Co-operative Central Bank"},{"id":"TDMX","name":"Dhanera Mercantile Co-operative Bank"},{"id":"TDPX","name":"Thodupuzha Urban Co-operative Bank"},{"id":"TDSX","name":"Nizamabad District Co-operative Central Bank"},{"id":"TECX","name":"Eenadu Co-operative Urban Bank"},{"id":"TEHX","name":"Tehri Garhwal Zila Sahkari Bank"},{"id":"TEMX","name":"Textile Manufacturers Co-operative Bank"},{"id":"TESX","name":"Textile Co-operative Bank of Surat"},{"id":"TETX","name":"Textile Traders Co-operative Bank"},{"id":"TFCX","name":"Fatehabad Central Co-operative Bank"},{"id":"TGBX","name":"Tripura Gramin Bank"},{"id":"TGCG","name":"Gokak Urban Co-operative Credit Bank"},{"id":"TGCX","name":"Tamluk-ghatal Central Co-operative Bank"},{"id":"TGDX","name":"Gondia District Central Co-operative Bank Gondia"},{"id":"TGMB","name":"Tumkur Grain Merchant's Co-operativeerate Bank"},{"id":"TGNX","name":"Gandhinagar Nagrik Co-operative Bank"},{"id":"TGUX","name":"Gandhinagar Urban Co-operative Bank"},{"id":"THCX","name":"Hooghly Co-operative Credit Bank"},{"id":"THOX","name":"Thoothukudi District Central Co-operative Bank"},{"id":"THRS","name":"Thrissur District Co-operative Bank"},{"id":"THRX","name":"Raichur District Central Co-operative Bank"},{"id":"THWX","name":"Howrah District Central Co-operative Bank"},{"id":"TIDX","name":"Thiruvannamalai District Central Co-operative Bank"},{"id":"TIRX","name":"Tirunelveli District Central Co-operative Bank"},{"id":"TJAX","name":"Jaisalmer Central Co-operative Bank"},{"id":"TJBX","name":"Janata Co-operative Bank Sadalga"},{"id":"TJCX","name":"Thanjavur Central Co-operative Bank"},{"id":"TJDX","name":"Jalgaon District Central Co-operative Bank Jalgaon"},{"id":"TJMX","name":"Jaynagar Mozilpur Peoples Co-operative Bank"},{"id":"TJNX","name":"Jamnagar Mahila Sahakari Bank"},{"id":"TJSB","name":"Thane Janata Sahakari Bank"},{"id":"TKAX","name":"Karjan Nagrik Sahakari Bank"},{"id":"TKCX","name":"Kakatiya Co-operative Urban Bank"},{"id":"TKDX","name":"Kannur District Co-operative Bank"},{"id":"TKTX","name":"Kottakkal Co-operative Urban Bank"},{"id":"TKUX","name":"Karan Urban Co-operative Bank"},{"id":"TLPX","name":"Lunawada Peoples Co-operative Bank"},{"id":"TMAX","name":"Madanapalle Co-operative Town Bank"},{"id":"TMBL","name":"Tamilnadu Mercantile Bank"},{"id":"TMBX","name":"Mangalore Catholic Co-operative Bank"},{"id":"TMCX","name":"Motihari Central Co-operative Bank"},{"id":"TMNX","name":"Mahanagar Co-operative Urban Bank"},{"id":"TMPX","name":"Midnapore Peoples Co-operative Bank"},{"id":"TMSC","name":"Mysore Silk Cloth Merchants Co-Operative Bank"},{"id":"TMSX","name":"Modasa Nagarik Sahkari Bank"},{"id":"TMTX","name":"Mangalore Co-operative Town Bank"},{"id":"TMUX","name":"Mahila Urban Co-operative Bank"},{"id":"TNBX","name":"Meghraj Nagarik Sahakari Bank"},{"id":"TNCX","name":"National Central Co-operative Bank Bettiah"},{"id":"TNDC","name":"Thiruvananthapuram District Co-operative Bank"},{"id":"TNEX","name":"Nehrunagar Co-operative Bank"},{"id":"TNHX","name":"Nakodar Hindu Urban Co-operative Bank"},{"id":"TNIX","name":"Tamilnadu Industrial Co-operative Bank"},{"id":"TNKX","name":"Neela Krishna Co-operative Urban Bank"},{"id":"TNMX","name":"Nanded Merchants Co-operative Bank Nanded"},{"id":"TNSC","name":"Tamilnadu State Apex Co-operative Bank"},{"id":"TNUX","name":"Nandura Urban Co-operative Bank Nandura"},{"id":"TOCX","name":"Ottapalam Co-operative Urban Bank"},{"id":"TPCX","name":"Patliputra Central Co-operative Bank"},{"id":"TPDX","name":"Prakasam District Co-operative Central Bank"},{"id":"TPSX","name":"Tripura State Co-operative Bank"},{"id":"TPUX","name":"Urban Co-operative Bank No 1758 Perinthalmanna"},{"id":"TRAX","name":"Transport Co-operative Bank"},{"id":"TRDX","name":"Tiruchirapalli Dist. Cent Co-operative Bank"},{"id":"TSAB","name":"Telangana State Co-operative Apex Bank"},{"id":"TSAX","name":"Satana Merchants Co-operative Bank, Satana"},{"id":"TSBX","name":"Sasaram Bhabhua Central Co-operative Bank"},{"id":"TSCX","name":"Santragachi Co-operative Bank"},{"id":"TSDX","name":"District Co-operative Central Bank Srikakul"},{"id":"TSIX","name":"Shillong Co-operative Urban Bank"},{"id":"TSMX","name":"Sardargunj Mercantile Co-operative Bank Patan"},{"id":"TSNX","name":"Shoranur Co-operative Urban Bank"},{"id":"TSPX","name":"Sathamba Peoples Co-operative Bank"},{"id":"TSSX","name":"S.S.K Co-Operative Bank"},{"id":"TSUX","name":"Saurashtra Co-operative Bank"},{"id":"TTBX","name":"Taliparamba Co-operative Urban Bank"},{"id":"TTCB","name":"Textile Traders Co-operative Bank"},{"id":"TTCX","name":"Tarn Taran Central Co-operative Bank"},{"id":"TTGX","name":"Tasgaon Urban Co-operative Banktasgaon"},{"id":"TTLX","name":"Textile Co-operative Bank"},{"id":"TTUX","name":"Tirur Urban Co-operative Bank"},{"id":"TUBX","name":"Trichur Urban Co-operative Bank"},{"id":"TUCL","name":"The Union Co-operative Bank Mahinagar"},{"id":"TUCX","name":"Tirupati Urban Co-operative Bank"},{"id":"TUDX","name":"Urban Co-operative Bank Dharangaon"},{"id":"TUMX","name":"Udaipur Mahila Urban Co-operative Bank"},{"id":"TUNX","name":"Union Co-operative Bank"},{"id":"TUOX","name":"Urban Co-operative Bank Saharanpur"},{"id":"TUPX","name":"Uttarsanda Peoples Co-operative Bank Uttarsanda"},{"id":"TURX","name":"Tura Urban Co-operative Bank"},{"id":"TVBX","name":"Vellala Co-operative Bank"},{"id":"TVDX","name":"District Co-operative Central Bank Vizianagaram"},{"id":"TVPX","name":"Veraval Peoples Co-operative Bank"},{"id":"TVUX","name":"Vita Urban Co-operative Bank"},{"id":"TYCX","name":"Shree Thyagaraja Co-operative Bank"},{"id":"UBBX","name":"Urban Co-operative Bank Basti"},{"id":"UBGX","name":"Uttar Bihar Gramin Bank"},{"id":"UBIN","name":"Union Bank of India"},{"id":"UCBA","name":"UCO Bank"},{"id":"UCBS","name":"Utkal Co-operative Banking Society"},{"id":"UCBX","name":"Urban Co-operative Bank Bareilly"},{"id":"UCCX","name":"Udaipur Central Co-operative Bank"},{"id":"UCDX","name":"Urban Co-operative Bank Dehradun"},{"id":"UCUX","name":"Universal Co-operative Urban Bank"},{"id":"UGBX","name":"Utkal Grameen Bank"},{"id":"UICX","name":"United India Co-operative Bank"},{"id":"UJSX","name":"Unjha Nagarik Sahakari Bank"},{"id":"UJVN","name":"Ujjivan Small Finance Bank"},{"id":"UKGX","name":"Uttarbanga Kshetriya Gramin Bank"},{"id":"UMAX","name":"Uma Co-operative Bank"},{"id":"UMCX","name":"Umreth Urban Co-operative Bank"},{"id":"UMSX","name":"Udaipur Mahila Samridhi Urban Co-operative Bank"},{"id":"UMUX","name":"Umiya Urban Co-operative Bank"},{"id":"UNAX","name":"Una Peoples Co-operative Bank"},{"id":"UNIX","name":"United Co-operative Bank"},{"id":"UNMX","name":"United Mercantile Co-operative Bank"},{"id":"UNSX","name":"Unava Nagrik Sahakari Bank"},{"id":"UOVB","name":"United Overseas Bank"},{"id":"UPCX","name":"Uttar Pradesh Co-operative Bank"},{"id":"URBN","name":"Urban Co-operative Bank Perinthalmanna"},{"id":"URCX","name":"Urban Co Operativa Bank Siddharthnagar"},{"id":"URDX","name":"Urban Co-operative Bank Budaun"},{"id":"URMX","name":"Urban Co-operative Bank Mainpuri"},{"id":"UROX","name":"Urban Co-operative Bank Rourkela"},{"id":"USFB","name":"Ujjivan Small Finance Bank"},{"id":"USNX","name":"Udham Singh Nagar District Co-operative Bank"},{"id":"UTBI","name":"United Bank of India"},{"id":"UTBX","name":"Uttarpara Co-operative Bank"},{"id":"UTCX","name":"Uttrakhand Co-operative Bank"},{"id":"UTGX","name":"Uttarakhand Gramin Bank"},{"id":"UTIB","name":"Axis Bank"},{"id":"UTKS","name":"Utkarsh Small Finance Bank"},{"id":"UTKX","name":"Uttarakhand State Co-operative Bank"},{"id":"UTZX","name":"Uttarkashi Zila Sahkari Bank"},{"id":"UUCX","name":"Udaipur Urban Co-operative Bank"},{"id":"VADX","name":"Valsad District Central Co-operative Bank"},{"id":"VAIX","name":"Vaishya Sahakari Bank Mumbai"},{"id":"VANX","name":"Vaishya Nagari Sahakari Bank"},{"id":"VARA","name":"Varachha Co-operative Bank"},{"id":"VASJ","name":"Vasai Janata Sahakari Bank"},{"id":"VASX","name":"Vyaparik Audhyogik Sahakari Bank Ktd"},{"id":"VAUX","name":"Valmiki Urban Co-operative Bank,pathri"},{"id":"VCAX","name":"Vaish Co-operative Adarsh Bank"},{"id":"VCBX","name":"Vishwas Co-operative Bank"},{"id":"VCCX","name":"Shri Veershaiv Co-operative Bank"},{"id":"VCNB","name":"Vaish Co-operative New Bank"},{"id":"VCOB","name":"The Vijay Co-operative Bank"},{"id":"VCOX","name":"Vita Merchants Co-operative Bank"},{"id":"VDCX","name":"Villupuram District Central Co-operative Bank"},{"id":"VDYX","name":"Vidyanand Co-operative Bank"},{"id":"VEDX","name":"Vellore District Central Co-operative Bank"},{"id":"VERX","name":"Veraval Mercantile Co-operative Bank"},{"id":"VGBX","name":"Vananchal Gramin Bank"},{"id":"VHDX","name":"Vaishali District Central Co-operative Bank"},{"id":"VICX","name":"Vijay Commercial Co-operative Bank"},{"id":"VIDX","name":"Vidyasagar Central Co-operative Bank"},{"id":"VIJB","name":"Vijaya Bank"},{"id":"VIJX","name":"Vijay Co-operative Bank"},{"id":"VIKX","name":"Vikramaditya Nagrik Sahakari Bank"},{"id":"VIMX","name":"Viramgam Mercantile Co-operative Bank"},{"id":"VIRX","name":"Virudhunagar District Central Co-operative Bank"},{"id":"VISX","name":"Visakhapatnam Co-operative Bank"},{"id":"VJSX","name":"Vasai Janata Sahakari Bank"},{"id":"VKCX","name":"Vima Kamgar Co-operative Bank"},{"id":"VKSX","name":"Vikas Sahakari Bank Limited Solapur"},{"id":"VMCX","name":"Vardhaman (mahila) Co-operative Urban Bank"},{"id":"VMMX","name":"Vaijapur Merchants Co-operative Bank"},{"id":"VMUX","name":"Vidarbha Merchants Urban Co-operative Bank"},{"id":"VNSX","name":"Vivekanand Nagrik Sahkari Bank Mydt"},{"id":"VRDX","name":"Vardhaman Co-operative Bank"},{"id":"VSBL","name":"Vishweshwar Sahakari Bank"},{"id":"VSBX","name":"Vidya Sahakari Bank"},{"id":"VSCX","name":"Vikas Souharda Co-operative Bank"},{"id":"VSSX","name":"Veerashaiva Sahakari Bank"},{"id":"VSVX","name":"Vaishali Shahari Vikas Co-op Bank"},{"id":"VUCX","name":"Vaidyanath Urban Co-operative Bank"},{"id":"VVCX","name":"Vallabh Vidyanagar Commercial Bank"},{"id":"VVSB","name":"Vasai Vikas Sahakari Bank"},{"id":"VYAX","name":"Vyavsayak Sahkari Bank"},{"id":"VYPX","name":"Vyapari Sahakari Bank Maryadit Solapur"},{"id":"VYSA","name":"ING Vysya Bank"},{"id":"WACX","name":"Waghodia Urban Co-operative Bank"},{"id":"WAIX","name":"Wai Urban Co-operative Bank"},{"id":"WARX","name":"Warangal District Co-operativeerative Central Bank"},{"id":"WAUX","name":"Wardhaman Urban Co-operative Bank Nagpur"},{"id":"WBSC","name":"West Bengal State Co-operative Bank"},{"id":"WCBX","name":"Women's Co-operative Bank"},{"id":"WDCX","name":"Wayanad District Co-operative Bank"},{"id":"WKGX","name":"Vidharbha Kokan Gramin Bank"},{"id":"WNBX","name":"Wana Nagirik Sahakari Bank"},{"id":"WPAC","name":"Westpac Banking Corporation"},{"id":"WRCX","name":"Warangal Urban Co-operativeerative Bank"},{"id":"WUCX","name":"Washim Urban Co-operative Bank."},{"id":"WZUX","name":"Wardha Zilla Parishad Emp Urban Co-operative Bank"},{"id":"XJKG","name":"J&K Grameen Bank"},{"id":"YADX","name":"Yavatmal District Central Co-operative Bank"},{"id":"YAVX","name":"Yavatmal Urban Co-operative Bank"},{"id":"YCBX","name":"Yashwant Co-operative Bank"},{"id":"YDCX","name":"Youth Development Co-operative Bank"},{"id":"YESB","name":"Yes Bank"},{"id":"YLNX","name":"Yadagiri Lakshmi Narsimha Swamy Co-operative Urban Bank "},{"id":"YMSX","name":"Yavatmal Mahila Sahakari Bank"},{"id":"YNCX","name":"Yamuna Nagar Central Co-operative Bank"},{"id":"YNSX","name":"Yeshwant Nagari Sahakari Bank"},{"id":"ZBBX","name":"Zila Sahkari Bank Bulandshahar"},{"id":"ZBSX","name":"Zila Sahkari Bank Mathura"},{"id":"ZCBL","name":"Zoroastrian Co-operative Bank"},{"id":"ZIBX","name":"Zila Sahkari Bank Bareilly"},{"id":"ZILX","name":"Zila Sahkari Bank Unnao"},{"id":"ZIMX","name":"Zila Sahkari Bank Mirzapur"},{"id":"ZISX","name":"Zila Sahakari Bank Lucknow"},{"id":"ZLLX","name":"Zila Sahkari Bank Lalitpur"},{"id":"ZMMX","name":"Zila Sahkari Bank Moradabad"},{"id":"ZRNB","name":"Rani Channamma Mahila Sahakari Bank"},{"id":"ZSAX","name":"Zila Sahkari Bank Mau"},{"id":"ZSBL","name":"Zila Sahkari Bank Ghaziabad"},{"id":"ZSBX","name":"Zila Sahkari Bank Bijnor"},{"id":"ZSGX","name":"Zila Sahkari Bank Garhwal Kotdwar"},{"id":"ZSHX","name":"Zila Sahkari Bank Haridwar"},{"id":"ZSJX","name":"Zila Sahkari Bank Jhansi"},{"id":"ZSKX","name":"Zila Sahkari Bank Kanpur"},{"id":"ZSLX","name":"Zila Sahkari Bank Lakhimpur Kheri"},{"id":"ZSMX","name":"Zila Sahkari Bank Meerut"}]}
